Workbook

Sheet IEEE - Estudos Primários
A1: IEEE - Estudos Primários
A2: Metadados organizados para rastreabilidade, auditoria e reprodução da RSL. Quantidade validada: 120 registros.
A4: ID do estudo | B4: Título | C4: Autores | D4: Ano | E4: Base de dados | F4: Tipo de estudo | G4: DOI | H4: Link | I4: Resumo | J4: Relevância para a pesquisa (Sim/Não) | K4: Questões de pesquisa atendidas (RQ1, RQ2, etc.) | L4: Observações
A5: P-IEEE-001 | B5: Self-Adaptive Large Language Model (LLM)-Based Multiagent Systems | C5: N. Nascimento; P. Alencar; D. Cowan | D5: 2023 | E5: IEEE Xplore | F5: Primário | G5: 10.1109/ACSOS-C58168.2023.00048 | H5: https://ieeexplore.ieee.org/stamp/stamp.jsp?arnumber=10336211 | I5: The complexity of managing multiagent systems (MASs) in autonomic computing can be mitigated using a self-adaptation approach, where systems are equipped to monitor and adjust themselves based on specific concerns. Communication in these systems is key given that in scenarios involving agent interaction, it enhances cooperation and reduces coordination challenges by enabling direct, clear information exchange. However, the tasks of boosting communication expressiveness within MASs and logically processing a multitude of variables in dynamic environments are still challenging. This paper presents a novel strategy: integrating large language models (LLMs) like GPT-based technologies into MASs to boost communication and agent autonomy. Our proposal encompasses the development of a novel LLM/GPT-based agent architecture, focusing not only on advanced conversation features but also on the reasoning and decision-making capacities of these models. This is grounded in the MAPE-K model, known for supporting system adaptability in dynamic environments. We illustrate our approach through a marketplace scenario. This work represents a paradigm shift in MAS self-adaptation, utilizing LLMs' capabilities and indicating further research opportunities to assess LLMs' applicability in more complex MAS scenarios. This could pave the way for more potent problem-solving capabilities and refined communication within MASs. | J5: Sim | K5: RQ2; RQ4; RQ5 | L5: Confirma aderência temática ao escopo MAS–LLM no título/resumo. Registro sem duplicidade aparente no conjunto consolidado.
A6: P-IEEE-002 | B6: Decentralized Multi-Agent System with Trust-Aware Communication | C6: Y. Ding; A. Twabi; J. Yu; L. Zhang; T. Kondo; H. Sato | D6: 2025 | E6: IEEE Xplore | F6: Primário | G6: 10.1109/ISPA67752.2025.00198 | H6: https://ieeexplore.ieee.org/stamp/stamp.jsp?arnumber=11245224 | I6: The emergence of Large Language Models (LLMs) is rapidly accelerating the development of autonomous multiagent systems (MAS), paving the way for the Internet of Agents. However, traditional centralized MAS architectures present significant challenges, including single points of failure, vulnerability to censorship, inherent scalability limitations, and critical trust issues. We propose a novel Decentralized Multi-Agent System (DMAS) architecture designed to overcome these fundamental problems by enabling trust-aware, scalable, and censorship-resistant interactions among autonomous agents. Our DMAS features a decentralized agent runtime underpinned by a blockchain-based architecture. We formalize a trust-aware communication protocol that leverages cryptographic primitives and on-chain operations to provide security properties: verifiable interaction cycles, communication integrity, authenticity, non-repudiation, and conditional confidentiality, which we further substantiate through a comprehensive security analysis. Our performance analysis validates the DMAS as a scalable and efficient solution for building trustworthy multi-agent systems. | J6: Sim | K6: RQ2; RQ4; RQ5 | L6: Confirma aderência temática ao escopo MAS–LLM no título/resumo. Registro sem duplicidade aparente no conjunto consolidado.
A7: P-IEEE-003 | B7: Architecture Design of Multi-Agent LLM Systems in Railway Data Governance | C7: Y. Cui; Y. Guo; C. Ren; C. Zhang; S. Shu; W. Peng; Z. Yin | D7: 2025 | E7: IEEE Xplore | F7: Primário | G7: 10.1109/HPCC67675.2025.00184 | H7: https://ieeexplore.ieee.org/stamp/stamp.jsp?arnumber=11207346 | I7: To address the challenges of manual dependency and complex management in railway data governance, and to promote data value realization, we propose DGMAS, a Data Governance Multi-Agent System based on Large Language Models (LLMs). The architectural design adopts a system comprising a mother system and three subsystems. The DGMAS comprises four critical phases: initialization, execution, re-planning, and failure attribution. Through this system, the process of railway data governance can be simulated, to help stakeholders anticipate potential issues and develop solutions, thereby supporting improved railway data governance. | J7: Sim | K7: RQ4; RQ5 | L7: Confirma aderência temática ao escopo MAS–LLM no título/resumo. Registro sem duplicidade aparente no conjunto consolidado.
A8: P-IEEE-004 | B8: Network Function Orchestration with LLM based Multi-Agent System | C8: J. Gemayel; A. Mokh | D8: 2025 | E8: IEEE Xplore | F8: Primário | G8: 10.1109/ICCWorkshops67674.2025.11162489 | H8: https://ieeexplore.ieee.org/stamp/stamp.jsp?arnumber=11162489 | I8: Large Language Models (LLMs) have significantly advanced the field of Natural Language Processing (NLP), enabling breakthroughs in contextual understanding, language generation, and reasoning. LLMs possess an intrinsic ability to act as orchestrators in dynamic and multifaceted environments. This work introduces a novel framework for dynamic function orchestration that leverages the reasoning capabilities of LLMs through Chain-of-Thought (CoT). The proposed framework comprises a sequence of three agents: a Semantic Router to direct user requests to the corresponding administrative domain, an Intent Translator to generate strategic plans utilizing a knowledge base containing 3GPP specifications, and a Resolver that selects and executes functions to fulfill the strategic plan. We systematically analyze the strengths and limitations of LLMs in collaborative orchestration, and demonstrate their capability to dynamically adapt to complex decision-making scenarios in the Telecom domain. | J8: Sim | K8: RQ4; RQ5 | L8: Confirma aderência temática ao escopo MAS–LLM no título/resumo. Registro sem duplicidade aparente no conjunto consolidado.
A9: P-IEEE-005 | B9: UML-based domain ontology modeling for multi-agent system | C9: Wei Liu; Zong-Tian Liu; Kun Shao | D9: 2003 | E9: IEEE Xplore | F9: Primário | G9: 10.1109/ICMLC.2003.1264511 | H9: https://ieeexplore.ieee.org/stamp/stamp.jsp?arnumber=1264511 | I9: In multi-agent application system, ontologies play an important role in facilitating the share and reuse of knowledge. In the field of object-oriented modeling, Unified Modeling Language (UML) has become standard modeling language and is widely supported by robust commercial tools. This paper shows how UML can be exploited to design the domain ontology model of multi-agent system at the agent level, in particular presents and ontology model diagram by extending the UML class diagram, and discusses the reasoning on UML-based ontology model. | J9: Não | K9: RQ3 | L9: Sem evidência suficiente para confirmar aderência temática ao escopo MAS–LLM no título/resumo. Registro sem duplicidade aparente no conjunto consolidado.
A10: P-IEEE-006 | B10: MultiFuzz: A Dense Retrieval-based Multi-Agent System for Network Protocol Fuzzing | C10: Y. Maklad; F. Wael; A. Hamdi; W. Elsersy; K. Shaban | D10: 2025 | E10: IEEE Xplore | F10: Primário | G10: 10.1109/AICCSA66935.2025.11315267 | H10: https://ieeexplore.ieee.org/stamp/stamp.jsp?arnumber=11315267 | I10: Traditional protocol fuzzing techniques, such as those employed by AFL-based systems, often lack effectiveness due to a limited semantic understanding of complex protocol grammars and rigid seed mutation strategies. Recent works, such as ChatAFL, have integrated Large Language Models (LLMs) to guide protocol fuzzing and address these limitations, pushing protocol fuzzers to wider exploration of the protocol state space. But ChatAFL still faces issues like unreliable output, LLM hallucinations, and assumptions of LLM knowledge about protocol specifications. This paper introduces MultiFuzz, a novel dense retrieval-based multi-agent system designed to overcome these limitations by integrating semantic-aware context retrieval, specialized agents, and structured tool-assisted reasoning. MultiFuzz utilizes agentic chunks of protocol documentation (RFC Documents) to build embeddings in a vector database for a retrieval-augmented generation (RAG) pipeline, enabling agents to generate more reliable and structured outputs, enhancing the fuzzer in mutating protocol messages with enhanced state coverage and adherence to syntactic constraints. The framework decomposes the fuzzing process into modular groups of agents that collaborate through chain-of-thought reasoning to dynamically adapt fuzzing strategies based on the retrieved contextual knowledge. Experimental evaluations on the Real-Time Streaming Protocol (RTSP) demonstrate that MultiFuzz significantly improves branch coverage and explores deeper protocol states and transitions over state-of-the-art (SOTA) fuzzers such as NSFuzz, AFLNet, and ChatAFL. By combining dense retrieval, agentic coordination, and language model reasoning, MultiFuzz establishes a new paradigm in autonomous protocol fuzzing, offering a scalable and extensible foundation for future research in intelligent agentic-based fuzzing systems. | J10: Sim | K10: RQ1; RQ2; RQ4; RQ5; RQ6 | L10: Confirma aderência temática ao escopo MAS–LLM no título/resumo. Registro sem duplicidade aparente no conjunto consolidado.
A11: P-IEEE-007 | B11: Control Industrial Automation System with Large Language Model Agents | C11: Y. Xia; N. Jazdi; J. Zhang; C. Shah; M. Weyrich | D11: 2025 | E11: IEEE Xplore | F11: Primário | G11: 10.1109/ETFA65518.2025.11205539 | H11: https://ieeexplore.ieee.org/stamp/stamp.jsp?arnumber=11205539 | I11: Traditional industrial automation systems require specialized expertise to operate and complex reprogramming to adapt to new processes. Large language models offer the intelligence to make them more flexible and easier to use. However, LLMs’ application in industrial automation settings is underexplored. This paper introduces a framework for integrating LLMs to achieve end-to-end control of industrial automation systems. At the core of the framework is an agent system designed for industrial automation tasks. A structured prompting method and an event-driven modeling mechanism provide the information for LLMs to perform reasoning on different context levels, allowing them to semantically interpret the information, generate production plans, and control operations on the automation system. Furthermore, this framework facilitates the creation of structured datasets for fine-tuning LLMs on this specific downstream application. Our contribution includes a formal system design, proof-of-concept implementation, and a method for generating task-specific datasets for LLM fine-tuning and testing. This approach enables a more adaptive automation system that can respond to spontaneous events, allowing intuitive system operation and configuration through natural language. Demo videos and detailed evaluation data are accessible on GitHub: https://github.com/YuchenXia/LLM4IAS. | J11: Não | K11: RQ4 | L11: Sem evidência suficiente para confirmar aderência temática ao escopo MAS–LLM no título/resumo. Registro sem duplicidade aparente no conjunto consolidado.
A12: P-IEEE-008 | B12: AutoHMA-LLM: Efficient Task Coordination and Execution in Heterogeneous Multi-Agent Systems Using Hybrid Large Language Models | C12: T. Yang; P. Feng; Q. Guo; J. Zhang; X. Zhang; J. Ning; X. Wang; Z. Mao | D12: 2025 | E12: IEEE Xplore | F12: Primário | G12: 10.1109/TCCN.2025.3528892 | H12: https://ieeexplore.ieee.org/stamp/stamp.jsp?arnumber=10839354 | I12: Heterogeneous multi-agent systems (HMAS) comprise various intelligent agents with specialized functions, such as drones, ground robots, and automated devices, working in coordinated settings. This paper presents AutoHMA-LLM, a novel framework that combines Large Language Models (LLMs) with classical control algorithms to address the challenges of task coordination and scheduling in complex, dynamic environments. The framework is designed with a multi-tier architecture, utilizing a cloud-based LLM as the central planner alongside device-specific LLMs and Generative Agents to improve task execution efficiency and accuracy. Specifically targeting dynamic scenarios, the system enhances resource utilization and stabilizes task execution through refined task scheduling and real-time feedback mechanisms. In experiments conducted across logistics, inspection, and search & rescue scenarios, AutoHMA-LLM demonstrated a 5.7% improvement in task completion accuracy, a 46% reduction in communication steps, and a 31% decrease in token usage and API calls compared to baseline methods. These results highlight our framework’s scalability and efficiency, offering substantial support for effective multi-agent collaboration in complex, resource-constrained environments. | J12: Sim | K12: RQ2; RQ4; RQ5 | L12: Confirma aderência temática ao escopo MAS–LLM no título/resumo. Registro também identificado em outra base ou categoria de busca.
A13: P-IEEE-009 | B13: Distributed Multi-Agent AI Systems: Scalability, Challenges, and Applications | C13: E. T. C. Chagas; A. Houmansadr; F. G. Guimarães; H. S. Ramos | D13: 2025 | E13: IEEE Xplore | F13: Primário | G13: 10.1109/ICDCSW63273.2025.00083 | H13: https://ieeexplore.ieee.org/stamp/stamp.jsp?arnumber=11262644 | I13: With the rapid advancement of generative AI and autonomous agents, multi-agent systems (MASs) have emerged as a key paradigm for enabling groups of intelligent agents to coordinate, share knowledge, and collaboratively solve complex problems in distributed environments. These systems not only inherit classical challenges from distributed computing-such as scalability, fault tolerance, and efficient communication-but also introduce novel issues arising from the dynamic and autonomous interactions between AI agents. As a result, MASs constitute an active research area with numerous open problems and nontrivial challenges. This tutorial provides a comprehensive introduction to MASs fundamentals, covering the state-of-the-art methodologies, core architectural patterns, and the critical trade-offs involved in designing scalable distributed applications. Participants will engage with both the theoretical underpinnings and practical implementations of MASs, leveraging LangGraph, a widely adopted framework for developing collaborative AI agent workflows. | J13: Não | K13: RQ2; RQ4; RQ5; RQ6 | L13: Sem evidência suficiente para confirmar aderência temática ao escopo MAS–LLM no título/resumo. Registro também identificado em outra base ou categoria de busca.
A14: P-IEEE-010 | B14: Enabling Synergistic Knowledge Sharing and Reasoning in Large Language Models with Collaborative Multi-Agents | C14: A. Das; S. -C. Chen; M. -L. Shyu; S. Sadiq | D14: 2023 | E14: IEEE Xplore | F14: Primário | G14: 10.1109/CIC58953.2023.00021 | H14: https://ieeexplore.ieee.org/stamp/stamp.jsp?arnumber=10429926 | I14: Despite the significant advancements in the field of Natural Language Processing (NLP), Large Language Models (LLMs) have shown limitations in performing complex tasks that require arithmetic, commonsense, and symbolic reasoning. Reasoning frameworks like ReAct, Chain-of-thought (CoT), Tree-of-thoughts (ToT), etc. have shown success but with limitations in solving long-form complex tasks. To address this, we pro-pose a knowledge-sharing and collaborative multi-agent assisted framework on LLMs that leverages the capabilities of existing reasoning frameworks and the collaborative skills of multi-agent systems (MASs). The objectives of the proposed framework are to overcome the limitations of LLMs, enhance their reasoning capabilities, and improve their performance in complex tasks. It involves generating natural language rationales and in-context few-shot learning via prompting, and integrates the reasoning techniques with efficient knowledge-sharing and communication-driven agent networks. The potential benefits of the proposed framework include saving time and money, improved efficiency for computationally intensive reasoning, and the ability to incor-porate multiple collaboration strategies for dynamically changing environments. | J14: Sim | K14: RQ2; RQ4; RQ5 | L14: Confirma aderência temática ao escopo MAS–LLM no título/resumo. Registro também identificado em outra base ou categoria de busca.
A15: P-IEEE-011 | B15: Onto2MAS: An Ontology-Based Framework for Automatic Multi-Agent System Generation | C15: C. Donzelli; S. A. Kidanu; R. Chbeir; Y. Cardinale | D15: 2016 | E15: IEEE Xplore | F15: Primário | G15: 10.1109/SITIS.2016.67 | H15: https://ieeexplore.ieee.org/stamp/stamp.jsp?arnumber=7907494 | I15: Multi-Agent Systems (MASs) have received muchattention in recent years because of their advantages on modelingcomplex distributed systems. Current modeling languages andmethodologies that support the construction of such systemsrequire the use of different tools to complete their design, development, and deployment. However, the development of MASsremains a complicated task, which demands time and specialprogramming skills. This paper proposes a framework, calledOnto2MAS, to provide developers an automatic generation ofMASs, based on an ontology to assist the easy definition of agentsinteraction and knowledge. With Onto2MAS, the complexityof the development process of MASs is reduced and an easyway to design uniform communication, messages exchanging, and generation of new knowledge in the system is provided. Todemonstrate the efficiency of our approach, we also present theresults of the experimental tests that we conducted with a firstimplementation of Onto2MAS, called OnToJade. | J15: Não | K15: RQ2; RQ3; RQ4 | L15: Sem evidência suficiente para confirmar aderência temática ao escopo MAS–LLM no título/resumo. Registro sem duplicidade aparente no conjunto consolidado.
A16: P-IEEE-012 | B16: Leveraging Multi-Agent Systems and Large Language Models for Diabetes Knowledge Graphs | C16: D. H. Ho; U. Das; R. Ho; Y. Lee | D16: 2024 | E16: IEEE Xplore | F16: Primário | G16: 10.1109/BigData62323.2024.10825608 | H16: https://ieeexplore.ieee.org/stamp/stamp.jsp?arnumber=10825608 | I16: This paper presents a novel framework for constructing a diabetes-specific knowledge graph (KG) using a streamlined multi-agent system powered by Gemini-based Large Language Models (LLMs). Leveraging insights from the 2016 National Diabetes Survey (NNDS) conducted by the National Diabetes Education Program (NDEP), the framework extracts critical variables related to diagnosis, risk perception, medical advice, and self-management practices across diverse U.S. populations. By processing data from the NNDS’s extensive 94-question survey, the methodology performs adaptive ontology mapping using APIs for six major medical standards (e.g., SNOMED CT, ICD-11), ensuring semantic interoperability. Relationships between variables are identified and structured using RDF, RDFS, and OWL standards. The integration of LLMs with ontology tools like Protégé enhances automation and scalability. Results demonstrate the framework’s effectiveness in generating contextually rich and clinically relevant knowledge graphs, providing a robust foundation for advancing healthcare informatics and personalized diabetes management. | J16: Sim | K16: RQ1; RQ3; RQ4; RQ5 | L16: Confirma aderência temática ao escopo MAS–LLM no título/resumo. Registro sem duplicidade aparente no conjunto consolidado.
... A124: P-IEEE-120 | B124: Programming Role Enactment through Reflection | C124: M. B. van Riemsdijk; V. Dignum; C. M. Jonker; H. Aldewereld | D124: 2011 | E124: IEEE Xplore | F124: Primário | G124: 10.1109/WI-IAT.2011.205 | H124: https://ieeexplore.ieee.org/stamp/stamp.jsp?arnumber=6040766 | I124: Organizational modeling languages are used to specify an agent organization in terms of its roles, organizational structure, norms, etc. Agents take part in organizations by playing one or more of the specified roles. Using such an organizational specification to organize a multi-agent system can support agents' effectiveness in attaining their purpose, or prevent certain undesired behavior from occurring. In this paper, we investigate the process of role enactment in organizations that have a so-called gatekeeper that is responsible for admitting agents to the organization, like the well-known OperA organizational modelling language. We propose an interaction protocol between gatekeeper and agents that want to play roles, resulting in admittance of agents to the organization (or rejection). We analyze which kinds of reasoning are needed for agents to participate in this protocol. In particular, agents need to be able to reason about whether they have the necessary capabilities to play a role in an organization. We make precise what it means to have a capability and propose to integrate reasoning about capabilities in agent programming languages using reflection. We show how this kind of reflection about capabilities can be used to program role enactment in the GOAL agent programming language. | J124: Não | K124: RQ2 | L124: Sem evidência suficiente para confirmar aderência temática ao escopo MAS–LLM no título/resumo. Registro sem duplicidade aparente no conjunto consolidado.

Sheet ACM - Estudos Primários
A1: ACM - Estudos Primários
A2: Metadados organizados para rastreabilidade, auditoria e reprodução da RSL. Quantidade validada: 120 registros.
A4: ID do estudo | B4: Título | C4: Autores | D4: Ano | E4: Base de dados | F4: Tipo de estudo | G4: DOI | H4: Link | I4: Resumo | J4: Relevância para a pesquisa (Sim/Não) | K4: Questões de pesquisa atendidas (RQ1, RQ2, etc.) | L4: Observações
A5: P-ACM-001 | B5: Large Language Model-Based Agents for Software Engineering: A Survey | C5: Liu, Junwei; Wang, Kaixin; Chen, Yixuan; Peng, Xin; Chen, Zhenpeng; Zhang, Lingming; Lou, Yiling | D5: 2026 | E5: ACM Digital Library | F5: Primário | G5: 10.1145/3796507 | H5: https://doi.org/10.1145/3796507 | I5: The recent advance in Large Language Models (LLMs) has shaped a new paradigm of AI agents, i.e., LLM-based agents. Compared to standalone LLMs, LLM-based agents substantially extend the versatility and expertise of LLMs by enhancing LLMs with the capabilities of perceiving and utilizing external resources and tools. To date, LLM-based agents have been applied and shown remarkable effectiveness in Software Engineering (SE). The synergy between multiple agents and human interaction brings further promise in tackling complex real-world SE problems. In this work, we present a comprehensive and systematic survey on LLM-based agents for SE. We collect 124 papers and categorize them from two perspectives, i.e., the SE and agent perspectives. In addition, we discuss open challenges and future directions in this critical domain. The repository of this survey is at . | J5: Não | K5: RQ5; RQ6 | L5: Sem evidência suficiente para confirmar aderência temática ao escopo MAS–LLM no título/resumo. Registro também identificado em outra base ou categoria de busca.
A6: P-ACM-002 | B6: A Survey on the Memory Mechanism of Large Language Model-based Agents | C6: Zhang, Zeyu; Dai, Quanyu; Bo, Xiaohe; Ma, Chen; Li, Rui; Chen, Xu; Zhu, Jieming; Dong, Zhenhua; Wen, Ji-Rong | D6: 2025 | E6: ACM Digital Library | F6: Primário | G6: 10.1145/3748302 | H6: https://doi.org/10.1145/3748302 | I6: Large language model (LLM)-based agents have recently attracted much attention from the research and industry communities. Compared with original LLMs, LLM-based agents are featured in their self-evolving capability, which is the basis for solving real-world problems that need long-term and complex agent-environment interactions. The key component to support agent-environment interactions is the memory of the agents. While previous studies have proposed many promising memory mechanisms, they are scattered in different papers, and there lacks a systematical review to summarize and compare these works from a holistic perspective, failing to abstract common and effective designing patterns for inspiring future studies. To bridge this gap, in this article, we propose a comprehensive survey on the memory mechanism of LLM-based agents. In specific, we first discuss “what is” and “why do we need” the memory in LLM-based agents. Then, we systematically review previous studies on how to design and evaluate the memory module. In addition, we also present many agent applications, where the memory module plays an important role. At last, we analyze the limitations of existing work and show important future directions. To keep up with the latest advances in this field, we create a repository at . | J6: Não | K6: RQ5; RQ6 | L6: Sem evidência suficiente para confirmar aderência temática ao escopo MAS–LLM no título/resumo. Registro também identificado em outra base ou categoria de busca.
A7: P-ACM-003 | B7: A Survey on the Optimization of Large Language Model-based Agents | C7: Du, Shangheng; Zhao, Jiabao; Shi, Jinxin; Xie, Zhentao; Jiang, Xin; Bai, Yanhong; He, Liang | D7: 2026 | E7: ACM Digital Library | F7: Primário | G7: 10.1145/3789261 | H7: https://doi.org/10.1145/3789261 | I7: With the rapid development of Large Language Models (LLMs), LLM-based agents have been widely adopted in various fields, becoming essential for autonomous decision-making and interactive tasks. However, current work typically relies on prompt design or fine-tuning strategies applied to vanilla LLMs, which often leads to limited effectiveness in complex agent-related environments. Although numerous recent studies have explored various strategies to optimize LLM-based agents for complex agent tasks, a systematic review summarizing and comparing these methods from a holistic perspective remains lacking. In this survey, we provide a comprehensive review of LLM-based agent optimization approaches, categorizing them into parameter-driven and parameter-free methods. We first focus on parameter-driven optimization, covering fine-tuning-based optimization, reinforcement learning-based optimization, and hybrid strategies, analyzing key aspects such as trajectory data construction, reward function design, and optimization algorithms. Additionally, we briefly discuss parameter-free strategies that optimize agent behavior through prompt engineering and external knowledge retrieval. Finally, we summarize the evaluation for agents, review key applications of LLM-based agents, and discuss the major challenges and promising future directions. A curated collection of the surveyed works is provided at https://github.com/YoungDubbyDu/LLM-Agent-Optimization. | J7: Não | K7: RQ5; RQ6 | L7: Sem evidência suficiente para confirmar aderência temática ao escopo MAS–LLM no título/resumo. Registro também identificado em outra base ou categoria de busca.
A8: P-ACM-004 | B8: ModelGen: Automating Semiconductor Parameter Extraction with Large Language Model Agents | C8: Wei, Yangbo; Huang, Li; Feng, Qi; Chen, Zhanfei; Yan, Jinlong; Lin, Ting-Jung; Huang, Zhen; Ren, Kun; Xing, Wei; He, Lei | D8: 2025 | E8: ACM Digital Library | F8: Primário | G8: 10.1145/3736165 | H8: https://doi.org/10.1145/3736165 | I8: Device models require large numbers of parameters to characterize complex physical effects. Although the latest advancements in machine learning and automated tools have drastically improved efficiency over the classic methods, they still demand a considerable amount of human intervention in the loop to gain accuracy. This drastically limits further automation. Inspired by the success of Multimodal Large Language Models (MLLMs) in addressing tasks across diverse fields, we propose ModelGen, the first in-depth study to leverage MLLMs with RAG (Retrieval-Augmented Generation) to significantly reduce human effort in parameter extraction for compact model. Our contributions include (1) Automated Agentic Workflow Construction that learns to build and refine extraction workflows through iterative optimization, (2) MLLM Judge, a visual scoring mechanism that evaluates fitting quality using actual device characteristic plots rather than simple numerical metrics, and (3) Model-specific RAG for providing relevant domain knowledge during the extraction process. Experimental results demonstrate that ModelGen achieves a 26.8%–33.1% improvement in pass@1,3,5 compared to base LLM methods. The system completes complex model extractions for BSIMs and ASM-HEMT in hours (up to 168\texttimes{} faster) rather than days or weeks, making parameter extraction more accessible to non-experts while maintaining professional engineer-level accuracy. | J8: Não | K8: Não identificado | L8: Sem evidência suficiente para confirmar aderência temática ao escopo MAS–LLM no título/resumo. Registro também identificado em outra base ou categoria de busca.
A9: P-ACM-005 | B9: MetaAgents: Large Language Model Based Agents for Decision-Making on Teaming | C9: Li, Yuan; Sun, Lichao; Zhang, Yixuan | D9: 2025 | E9: ACM Digital Library | F9: Primário | G9: 10.1145/3711032 | H9: https://doi.org/10.1145/3711032 | I9: Significant advancements have occurred in the application of Large Language Models (LLMs) for social simulations. Despite this, their abilities to perform teaming in task-oriented social events are underexplored. Such capabilities are crucial if LLMs are to effectively mimic human-like social behaviors and form efficient teams to solve tasks. To bridge this gap, we introduce MetaAgents, a social simulation framework populated with LLM-based agents. MetaAgents facilitates agent engagement in conversations and a series of decision making within social contexts, serving as an appropriate platform for investigating interactions and interpersonal decision-making of agents. In particular, we construct a job fair environment as a case study to scrutinize the team assembly and skill-matching behaviors of LLM-based agents. We take advantage of both quantitative metrics evaluation and qualitative text analysis to assess their teaming abilities at the job fair. Our evaluation demonstrates that LLM-based agents perform competently in making rational decisions to develop efficient teams. However, we also identify limitations that hinder their effectiveness in more complex team assembly tasks. Our work provides valuable insights into the role and evolution of LLMs in task-oriented social simulations. | J9: Não | K9: RQ4; RQ5 | L9: Sem evidência suficiente para confirmar aderência temática ao escopo MAS–LLM no título/resumo. Registro também identificado em outra base ou categoria de busca.
A10: P-ACM-006 | B10: Using LLMs in Generating Design Rationale for Software Architecture Decisions | C10: Zhou, Xiyu; Li, Ruiyin; Liang, Peng; Zhang, Beiqi; Shahin, Mojtaba; Li, Zengyang; Yang, Chen | D10: 2025 | E10: ACM Digital Library | F10: Primário | G10: 10.1145/3785010 | H10: https://doi.org/10.1145/3785010 | I10: Design Rationale (DR) for software architecture decisions refers to the reasoning underlying architectural choices, which provides valuable insights into the different phases of the architecting process throughout software development. However, in practice, DR is often inadequately documented due to a lack of motivation and effort from developers. With the recent advancements in Large Language Models (LLMs), their capabilities in text comprehension, reasoning, and generation may enable the generation and recovery of DR for architecture decisions. In this study, we evaluated the performance of LLMs in generating DR for architecture decisions. First, we collected 50 Stack Overflow (SO) posts, 25 GitHub issues, and 25 GitHub discussions related to architecture decisions to construct a dataset of 100 architecture-related problems. Then, we selected five LLMs to generate DR for the architecture decisions with three prompting strategies, including zero-shot, chain of thought (CoT), and LLM-based agents. With the DR provided by human experts as ground truth, the Precision of LLM-generated DR with the three prompting strategies ranges from 0.267 to 0.278, Recall from 0.627 to 0.715, and F1-score from 0.351 to 0.389. Besides, 64.45% to 69.42% of the arguments of DR not mentioned by human experts are also helpful, 4.12% to 4.87% of the arguments have uncertain correctness, and 1.59% to 3.24% of the arguments are potentially misleading. To further understand the trustworthiness and applicability of LLM-generated DR in practice, we conducted semi-structured interviews with six practitioners. Based on the experimental and interview results, we discussed the pros and cons of the three prompting strategies, the strengths and limitations of LLM-generated DR, and the implications for the practical use of LLM-generated DR. | J10: Não | K10: RQ4; RQ5 | L10: Sem evidência suficiente para confirmar aderência temática ao escopo MAS–LLM no título/resumo. Registro também identificado em outra base ou categoria de busca.
A11: P-ACM-007 | B11: Integrating Various Software Artifacts for Better LLM-based Bug Localization and Program Repair | C11: Feng, Qiong; Ma, Xiaotian; Sheng, Jiayi; Feng, Ziyuan; Song, Wei; Liang, Peng | D11: 2025 | E11: ACM Digital Library | F11: Primário | G11: 10.1145/3770581 | H11: https://doi.org/10.1145/3770581 | I11: LLMs have garnered considerable attention for their potential to streamline Automated Program Repair (APR). LLM-based approaches can either insert the correct code using an infilling-style technique or directly generate patches when provided with buggy methods, aiming for plausible patches to pass all tests. However, most of LLM-based APR methods rely on a single type of software information, such as issue descriptions or error stack traces, without fully leveraging a combination of diverse software artifacts. Human developers, in contrast, often use a range of information — such as debugging data, issue discussions, and error stack traces — to diagnose and fix bugs. Despite this, many LLM-based approaches do not explore which specific types of software information best assist in localizing and repairing software bugs. Addressing this gap is crucial for advancing LLM-based APR techniques.To investigate this and mimic the way human developers fix bugs, we propose DEVLoRe (short for DEVeloper Localization and Repair). In this framework, LLMs first use issue content (description and discussion) and stack error traces to localize buggy methods, then rely on debug information in buggy methods and issue content and stack error to localize buggy lines and generate valid patches. We evaluated the effectiveness of issue content, error stack traces, and debugging information in bug localization and automatic program repair. Our results show that while issue content and error stack is particularly effective in assisting LLMs with fault localization and program repair respectively, different types of software artifacts complement each other in addressing various bugs. By incorporating these three types of artifacts and using the Defects4J v2.0 dataset for evaluation, DEVLoRe successfully localizes 49.3% of single-method bugs and generates 56.0% plausible patches. Additionally, DEVLoRe can localize 47.6% of non-single-method bugs and generates 14.5% plausible patches. Moreover, our framework streamlines the end-to-end process from buggy source code to a complete repair, and achieves a 39.7% and 17.1% of single-method and non-single-method bug repair rate, outperforming current state-of-the-art APR methods. Furthermore, we re-implemented and evaluated our framework, demonstrating its effectiveness in resolving 9 unique issues compared to other state-of-the-art frameworks using the same or more advanced models on SWE-bench Lite. We also discussed whether a leading framework for Python code can be directly applied to Java code, or vice versa. The source code and experimental results of this work for replication are available at . | J11: Não | K11: RQ4 | L11: Sem evidência suficiente para confirmar aderência temática ao escopo MAS–LLM no título/resumo. Registro também identificado em outra base ou categoria de busca.
A12: P-ACM-008 | B12: LLMs May Not Be Human-Level Players, But They Can Be Testers: Measuring Game Difficulty with LLM Agents | C12: Xiao, Chang; Yang, Zixiaofan | D12: 2025 | E12: ACM Digital Library | F12: Primário | G12: 10.1145/3748634 | H12: https://doi.org/10.1145/3748634 | I12: Recent advances in Large Language Models (LLMs) have demonstrated their potential as autonomous agents across various tasks. One emerging application is the use of LLMs in playing games. In this work, we explore a practical problem for the gaming industry: Can LLMs be used to measure game difficulty? We evaluate the feasibility of using LLM agents to test game difficulty, focusing on two widely played games: Wordle and Slay the Spire. Our results reveal an interesting finding: although LLMs may not perform as well as the average human player, their performance, when guided by simple, generic prompting techniques, shows a statistically significant and strong correlation with difficulty indicated by human players. This suggests that LLMs could potentially serve as human-like agents for measuring game difficulty during the development process, as their assessments may align closely with those of human players. Based on our experiments, we also propose general principles and guidelines for integrating LLMs into the game testing workflow. | J12: Não | K12: RQ5 | L12: Sem evidência suficiente para confirmar aderência temática ao escopo MAS–LLM no título/resumo. Registro também identificado em outra base ou categoria de busca.
A13: P-ACM-009 | B13: Extended Reality Cybersickness Assessment via User Review Analysis | C13: Li, Shuqing; Zheng, Qisheng; Gao, Cuiyun; Feng, Jia; Lyu, Michael R. | D13: 2025 | E13: ACM Digital Library | F13: Primário | G13: 10.1145/3728933 | H13: https://doi.org/10.1145/3728933 | I13: In recent years, the extended reality (XR) software ecosystem has emerged as the next ubiquitous computing platform, as they provide users with immersive interactive experiences. However, XR ecosystem suffers from cybersickness problems, which would greatly affect user comfort and safety, leading to symptoms like headaches, disorientation, etc. That makes effective cybersickness assessment a timely and important question. The state-of-the-art methods of assessing the cybersickness of XR software typically monitor the biological metrics of users, during XR usage, which rely heavily on manual playtesting,sufferring from limited scalability issue. User reviews on XR app stores are informative for developers to learn the cybersickness ratings of their apps and the reasons behind. Nevertheless, the large number of user reviews can hardly be analyzed by developers manually, and most current automatic user review analysis methods can only provide coarse-grained or abstract results, such as extracting several high-level key topic groups discussed by reviews. Recent advancements in LLMs may bring new opportunities. However, directly leveraging LLMs for evaluating XR cybersickness is challenging because LLMs perform poorly on a large number of short texts, and their context window is limited. To address these challenges, we introduce XRCare, a comprehensive framework designed to automate the assessment of cybersickness and root cause reasoning for XR apps by resorting to fine-grained user review analysis. XRCare mainly includes three phases: (1) Insight pool construction, when XRCare collects the cybersickness analyzing chains and corresponding analyzing results from domain experts; (2) Reasoning graph construction, when XRCare dynamically extracts, categorizes, and maintains the reasons from user reviews that make users feel cybersickness on a self-evolving hierarchical graph; and (3) Multi-agent deductive cybersickness reasoning, which utilizes a multi-agent system to simulate diverse user demographics for analyzing and rating the intensity of cybersickness, as well as the causes of cybersickness. This structured approach allows XRCare to systematically identify, categorize, and address instances of cybersickness. For experiments, we construct a large-scale dataset consisting of 685,111 user reviews from 9,667 XR apps. Our evaluation shows that XRCare enhances the F1-score by 20.63% over the best-performing baseline and by 32.27% on average across all baselines, while also offering more accurate and detailed interpretability insights. | J13: Sim | K13: RQ4; RQ5 | L13: Confirma aderência temática ao escopo MAS–LLM no título/resumo. Registro também identificado em outra base ou categoria de busca.
A14: P-ACM-010 | B14: Large Language Models for Cyber Security: A Systematic Literature Review | C14: Xu, Hanxiang; Wang, Shenao; Li, Ningke; Wang, Kailong; Zhao, Yanjie; Chen, Kai; Yu, Ting; Liu, Yang; Wang, Haoyu | D14: 2025 | E14: ACM Digital Library | F14: Primário | G14: 10.1145/3769676 | H14: https://doi.org/10.1145/3769676 | I14: The rapid advancement of Large Language Models (LLMs) has opened up new opportunities for leveraging artificial intelligence in a variety of application domains, including cybersecurity. As the volume and sophistication of cyber threats continue to grow, there is an increasing need for intelligent systems that can automatically detect vulnerabilities, analyze malware, and respond to attacks. In this survey, we conduct a comprehensive review of the literature on the application of LLMs in cybersecurity (LLM4Security). By comprehensively collecting over 40K relevant papers and systematically analyzing 185 papers from top security and software engineering venues, we aim to provide a holistic view of how LLMs are being used to solve diverse problems across the cybersecurity domain.Through our analysis, we identify several key findings. First, we observe that LLMs are being applied to an expanding range of cybersecurity tasks, including vulnerability detection, malware analysis, and network intrusion detection. Second, we analyze application trends of different LLM architectures (such as encoder-only, encoder-decoder, and decoder-only) across security domains. Third, we identify increasingly sophisticated techniques for adapting LLMs to cybersecurity, such as advanced fine-tuning, prompt engineering, and external augmentation strategies. A significant emerging trend is the use of LLM-based autonomous agents, which represent a paradigm shift from single-task execution to orchestrating complex, multi-step security workflows. Furthermore, we find that the datasets used for training and evaluating LLMs are often limited, highlighting the need for more comprehensive datasets and the use of LLMs for data augmentation. Finally, we discuss the main challenges and opportunities for future research, including the need for more interpretable models, addressing the inherent security risks of LLMs, and their potential for proactive defense.Overall, our survey provides a comprehensive overview of the current state-of-the-art in LLM4Security and identifies several promising directions for future research. We believe that the insights and findings presented in this survey will contribute to the growing body of knowledge on the application of LLMs in cybersecurity and provide valuable guidance for researchers and practitioners working in this field. | J14: Não | K14: RQ5; RQ6 | L14: Sem evidência suficiente para confirmar aderência temática ao escopo MAS–LLM no título/resumo. Registro também identificado em outra base ou categoria de busca.
A15: P-ACM-011 | B15: Large Language Models for EDA: Future or Mirage? | C15: He, Zhuolun; Pu, Yuan; Wu, Haoyuan; Qiu, Tairu; Yu, Bei | D15: 2025 | E15: ACM Digital Library | F15: Primário | G15: 10.1145/3736167 | H15: https://doi.org/10.1145/3736167 | I15: In this article, we explore the burgeoning intersection of large language models (LLMs) and electronic design automation (EDA). We critically assess whether LLMs represent a transformative future for EDA or merely a fleeting mirage. By organizing existing research into four critical domains of EDA—code generation, verification and debugging, knowledge representation and retrieval, and optimization/modeling—we provide a comprehensive overview of the current state-of-the-art. The survey concludes with a 5-level roadmap to guide the progressive integration and advancement of LLMs in EDA. Ultimately, this article aims to provide a comprehensive, evidence-based perspective on the role of LLMs in shaping the future of EDA. | J15: Não | K15: RQ1 | L15: Sem evidência suficiente para confirmar aderência temática ao escopo MAS–LLM no título/resumo. Registro também identificado em outra base ou categoria de busca.
A16: P-ACM-012 | B16: cGenEDA: Code-Generation for Electronic Design Optimization | C16: Tremuel, Philipp; Benites, Fernando; W\"{u}rsch, Christoph; H\"{u}gel, Ulf; Wolf, Florian; B\"{u}chel, Andreas; Gavves, Efstratios | D16: 2026 | E16: ACM Digital Library | F16: Primário | G16: 10.1145/3800953 | H16: https://doi.org/10.1145/3800953 | I16: Addressing inverse design problems in engineering generally requires managing complex challenges. Traditionally, such systems are optimized by manually setting up a model in a numerical simulation software and applying parameter optimization. Topology changes and variable parameter sets result in challenging mixed-integer optimization problems. Such problems are hard to solve automatically; that’s why they normally need to be initialized manually with high effort by the design engineer. Generative probabilistic models, like Large Language Models (LLMs), can efficiently produce diverse, valid design concepts that are fully parameterizable, simulatable, and optimizable. We introduce cGenEDA, a Co-Pilot—a system based on multiple LLM agents using in-context prompting to coordinate these tasks, providing a seamless, adaptable toolchain for automated design generation, optimization problem definition, and design automation. Our approach demonstrates that long, interacting simulation model code sequences can be generated accurately and directly used as model input for domain-specific simulators for precise forward simulations. Simultaneously, cGenEDA will set up the optimization problem, combine it with well-known, black-box optimization algorithms, and efficiently solve inverse design problems. | J16: Não | K16: RQ5 | L16: Sem evidência suficiente para confirmar aderência temática ao escopo MAS–LLM no título/resumo. Registro também identificado em outra base ou categoria de busca.
... A124: P-ACM-120 | B124: Models of machines and computation for mapping in multicomputers | C124: Norman, Michael G.; Thanisch, Peter | D124: 1993 | E124: ACM Digital Library | F124: Primário | G124: 10.1145/158439.158908 | H124: https://doi.org/10.1145/158439.158908 | I124: Resumo não informado no metadado. | J124: Não | K124: Não identificado | L124: Sem evidência suficiente para confirmar aderência temática ao escopo MAS–LLM no título/resumo. Registro também identificado em outra base ou categoria de busca.

Sheet Web of Science - Primários
A1: Web of Science - Primários
A2: Metadados organizados para rastreabilidade, auditoria e reprodução da RSL. Quantidade validada: 85 registros.
A4: ID do estudo | B4: Título | C4: Autores | D4: Ano | E4: Base de dados | F4: Tipo de estudo | G4: DOI | H4: Link | I4: Resumo | J4: Relevância para a pesquisa (Sim/Não) | K4: Questões de pesquisa atendidas (RQ1, RQ2, etc.) | L4: Observações
A5: P-WOS-001 | B5: Multi-Agentic LLMs for Personalizing STEM Texts | C5: Vaccaro Jr, Michael; Friday, Mikayla; Zaghi, Arash | D5: 2025 | E5: Web of Science | F5: Primário | G5: 10.3390/app15137579 | H5: https://doi.org/10.3390/app15137579 | I5: Multi-agent large language models promise flexible, modular architectures for delivering personalized educational content. Drawing on a pilot randomized controlled trial with middle school students (n = 23), we introduce a two-agent GPT-4 framework in which a Profiler agent infers learner-specific preferences and a Rewrite agent dynamically adapts science passages via an explicit message-passing protocol. We implement structured system and user prompts as inter-agent communication schemas to enable real-time content adaptation. The results of an ordinal logistic regression analysis hinted that students may be more likely to prefer texts aligned with their profile, demonstrating the feasibility of multi-agent system-driven personalization and highlighting the need for additional work to build upon this pilot study. Beyond empirical validation, we present a modular multi-agent architecture detailing agent roles, communication interfaces, and scalability considerations. We discuss design best practices, ethical safeguards, and pathways for extending this framework to collaborative agent networks-such as feedback-analysis agents-in K-12 settings. These results advance both our theoretical and applied understanding of multi-agent LLM systems for personalized learning. | J5: Sim | K5: RQ1; RQ2; RQ4; RQ5 | L5: Confirma aderência temática ao escopo MAS–LLM no título/resumo. Registro sem duplicidade aparente no conjunto consolidado.
A6: P-WOS-002 | B6: UsmleGPT: An AI application for developing MCQs via multi-agent system | C6: Jiang, Zhehan; Feng, Shicong | D6: 2025 | E6: Web of Science | F6: Primário | G6: 10.1016/j.simpa.2025.100742 | H6: https://doi.org/10.1016/j.simpa.2025.100742 | I6: Driven by the trending multi-agent system (MAS) that harnesses collective intelligence from numerous large language models (LLMs), UsmleGPT is a Python-based application designed to enhance LLM-generated content tailored for the USMLE Step 1 scenario. The MAS aligns with the NBME's framework, incorporating advanced prompt strategies to guide each LLM through their respective tasks and specialties. This enables UsmleGPT to surpass conventional practices in automating item generation. Beyond the original script, a freely accessible, user-friendly website complements the tool, facilitating its adoption. UsmleGPT represents a breakthrough in medical education, transforming medical exam preparation and setting new standards for high-stakes medical assessments. | J6: Sim | K6: RQ4 | L6: Confirma aderência temática ao escopo MAS–LLM no título/resumo. Registro sem duplicidade aparente no conjunto consolidado.
A7: P-WOS-003 | B7: Intent-Based Infrastructure and Service Orchestration Using Agentic-AI | C7: Brodimas, Dimitrios; Birbas, Alexios; Kapolos, Dimitrios; Denazis, Spyros | D7: 2025 | E7: Web of Science | F7: Primário | G7: 10.1109/OJCOMS.2025.3600706 | H7: https://doi.org/10.1109/OJCOMS.2025.3600706 | I7: This paper introduces a novel framework that integrates agentic Artificial Intelligence (AI) with Intent-Based Networks (IBN) to enable autonomous management, configuration, and optimization of mobile network services and resources. Leveraging the advanced reasoning and natural language processing capabilities of an Large Language Model (LLM), the proposed architecture translates high-level user intents into precise network actions, facilitating user-friendly and scalable network orchestration. The framework employs a distributed multi-agent system, where specialized agents collaborate to decompose user intents, provide computational infrastructure, and deploy services using industry-standard Infrastructure-as-Code (IaC) tools. By supporting natural language interactions, the system reduces operational complexity and enhances accessibility for users with varying technical expertise. Experimental evaluations demonstrate significant improvements in task completion rates, response accuracy, and operational efficiency compared to traditional manual methods, particularly for complex network management tasks. In essence, this work creates an intelligent network orchestration framework that adapts to user needs by automatically configuring network and computing resources while operating with minimal human intervention. | J7: Sim | K7: RQ3; RQ4 | L7: Confirma aderência temática ao escopo MAS–LLM no título/resumo. Registro também identificado em outra base ou categoria de busca.
A8: P-WOS-004 | B8: ClinicalAgent: Clinical Trial Multi-Agent System with Large Language Model-based Reasoning | C8: Yue, Ling; Xing, Sixue; Chen, Jintai; Fu, Tianfan | D8: 2024 | E8: Web of Science | F8: Primário | G8: 10.1145/3698587.3701359 | H8: https://doi.org/10.1145/3698587.3701359 | I8: Large Language Models (LLMs) and multi-agent systems have shown impressive capabilities in natural language tasks but face challenges in clinical trial applications, primarily due to limited access to external knowledge. Recognizing the potential of advanced clinical trial tools that aggregate and predict based on the latest medical data, we propose an integrated solution to enhance their accessibility and utility. We introduce Clinical Agent System (ClinicalAgent), a clinical multi-agent system designed for clinical trial tasks, leveraging GPT-4, multi-agent architectures, LEAST-TO-MOST, and ReAct reasoning technology. This integration not only boosts LLM performance in clinical contexts but also introduces novel functionalities. The proposed method achieves competitive predictive performance in clinical trial outcome prediction (0.7908 PR-AUC), obtaining a 0.3326 improvement over the standard prompt Method. Publicly available code can be found at https://github.com/LeoYML/clinical-agent. | J8: Sim | K8: RQ1; RQ3; RQ5 | L8: Confirma aderência temática ao escopo MAS–LLM no título/resumo. Registro sem duplicidade aparente no conjunto consolidado.
A9: P-WOS-005 | B9: Architecture of Multi-agent System for Automatic Code Template Maintenance | C9: Akik, Elena; Viatica, Marko; Dimitrieski, Vladimir; Kordi, Slavica; Ristie, Sonja | D9: 2026 | E9: Web of Science | F9: Primário | G9: 10.1007/978-3-032-05727-3\_26 | H9: https://doi.org/10.1007/978-3-032-05727-3\_26 | I9: In modern software engineering, template-based code generation, and in particular Large Language Model (LLM) driven code synthesis, have been identified as key enablers of developer productivity in environments in which complex, predefined components are subject to continuous adaptation to evolving requirements. However, the maintenance of code generator templates is frequently performed as a manual, error prone task when dependencies on external specifications or components are present, especially when they change often. To address this gap, a Multi-Agent System (MAS) is proposed, in which LLMs are relied upon for the interpretation of template code, and Model-Driven Software Development (MDSD) principles are applied for the structured representation of templates. In this system, specialized agents are tasked with detecting and interpreting changes in external specifications, performing targeted updates to template code, and validating consistency against a canonical model. Communication among agents, and the storage of semantic embeddings of template fragments and domain models, are managed through a vector database, thereby enabling retrieval of prior template versions and reasoning over them. The proposed solution is to be integrated into an existing MDSD solution for uniform access to vector databases as proof of concept. | J9: Sim | K9: RQ1; RQ2; RQ4 | L9: Confirma aderência temática ao escopo MAS–LLM no título/resumo. Registro sem duplicidade aparente no conjunto consolidado.
A10: P-WOS-006 | B10: AutoHMA-LLM: Efficient Task Coordination and Execution in Heterogeneous Multi-Agent Systems Using Hybrid Large Language Models | C10: Yang, Tingting; Feng, Ping; Guo, Qixin; Zhang, Jindi; Zhang, Xiufeng; Ning, Jiahong; Wang, Xinghan; Mao, Zhongyang | D10: 2025 | E10: Web of Science | F10: Primário | G10: 10.1109/TCCN.2025.3528892 | H10: https://doi.org/10.1109/TCCN.2025.3528892 | I10: Heterogeneous multi-agent systems (HMAS) comprise various intelligent agents with specialized functions, such as drones, ground robots, and automated devices, working in coordinated settings. This paper presents AutoHMA-LLM, a novel framework that combines Large Language Models (LLMs) with classical control algorithms to address the challenges of task coordination and scheduling in complex, dynamic environments. The framework is designed with a multi-tier architecture, utilizing a cloud-based LLM as the central planner alongside device-specific LLMs and Generative Agents to improve task execution efficiency and accuracy. Specifically targeting dynamic scenarios, the system enhances resource utilization and stabilizes task execution through refined task scheduling and real-time feedback mechanisms. In experiments conducted across logistics, inspection, and search \& rescue scenarios, AutoHMA-LLM demonstrated a 5.7\% improvement in task completion accuracy, a 46\% reduction in communication steps, and a 31\% decrease in token usage and API calls compared to baseline methods. These results highlight our framework's scalability and efficiency, offering substantial support for effective multi-agent collaboration in complex, resource-constrained environments. | J10: Sim | K10: RQ2; RQ4; RQ5 | L10: Confirma aderência temática ao escopo MAS–LLM no título/resumo. Registro também identificado em outra base ou categoria de busca.
A11: P-WOS-007 | B11: Multi-Agent Collaborative Reasoning via Cloud-Edge Framework | C11: Zeng, Jiandian; Liao, Junjie; Sun, Shaochen; Zhang, Guangxue; Xu, Changfu; Liu, Huaijin; Li, Yang | D11: 2026 | E11: Web of Science | F11: Primário | G11: 10.1109/MNET.2026.3651036 | H11: https://doi.org/10.1109/MNET.2026.3651036 | I11: Large Language Model (LLM)-based agents have significantly advanced the reasoning and problem-solving capabilities of intelligent systems. As tasks grow more complex, there is an increasing need to shift from single-agent framework to Multi-Agent Systems (MAS) for enhanced collaborative performance. Achieving better performance typically requires deploying large-scale LLMs, however, it poses significant challenges on resource-constrained edge devices. In addition, most MAS adopt a fully connected communication topology and require multiple rounds of interaction, resulting in considerable communication redundancy and increased computational overhead. To address the issues, in this paper, we propose a Directed Acyclic Graph-based Multi-Agent System (DAG-MAS) via cloud-edge framework for collaborative reasoning. Specifically, considering the limited resources on the edge, we utilize a 72B-LLM in the cloud finetunes a lightweight Small Language Model (SLM) for edge deployment. To generate a one round interaction graph, the SLM is further employed to analyze task requirements and determine optimal communication topology, minimizing overhead while enabling effective information exchange. Extensive experiments and analyses on four reasoning datasets demonstrate the superiority of our approach compared to several benchmark methods, validating the effectiveness in achieving higher reasoning performance with lower communication costs. | J11: Sim | K11: RQ2; RQ4; RQ5 | L11: Confirma aderência temática ao escopo MAS–LLM no título/resumo. Registro também identificado em outra base ou categoria de busca.
A12: P-WOS-008 | B12: A Hybrid Perplexity-MAS Framework for Proactive Jailbreak Attack Detection in Large Language Models | C12: Wang, Ping; Li, Hao-Cyuan; Lin, Hsiao-Chung; Lin, Wen-Hui; Wu, Fang-Ci; Xie, Nian-Zu; Yang, Zhon-Ghan | D12: 2025 | E12: Web of Science | F12: Primário | G12: 10.3390/app152413190 | H12: https://doi.org/10.3390/app152413190 | I12: Jailbreak attacks (JAs) represent a sophisticated subclass of adversarial threats wherein malicious actors craft strategically engineered prompts that subvert the intended operational boundaries of large language models (LLMs). These attacks exploit latent vulnerabilities in generative AI architectures, allowing adversaries to circumvent established safety protocols and illicitly induce the model to output prohibited, unethical, or harmful content. The emergence of such exploits underscores critical gaps in the security and controllability of modern AI systems, raising profound concerns about their societal impact and deployment in sensitive environments. In response, this study introduces an innovative defense framework that synergistically integrates language model perplexity analysis with a Multi-Agent System (MAS)-oriented detection architecture. This hybrid design aims to fortify the resilience of LLMs by proactively identifying and neutralizing jailbreak attempts, thereby ensuring the protection of user privacy and ethical integrity. The experimental setup adopts a query-driven adversarial probing strategy, in which jailbreak prompts are dynamically generated and injected into the open-source LLaMA-2 model to systematically explore potential vulnerabilities. To ensure rigorous validation, the proposed framework will be evaluated using a custom jailbreak detection benchmark encompassing metrics such as Attack Success Rate (ASR), Defense Success Rate (DSR), Defense Pass Rate (DPR), False Positive Rate, Benign Pass Rate (BPR), and End-to-End Latency. Through iterative experimentation and continuous refinement, this work endeavors to advance the defensive capabilities of LLM-based systems, enabling more trustworthy, secure, and ethically aligned deployment of generative AI in real-world environments. | J12: Sim | K12: RQ4; RQ5 | L12: Confirma aderência temática ao escopo MAS–LLM no título/resumo. Registro sem duplicidade aparente no conjunto consolidado.
A13: P-WOS-009 | B13: Segment, Recommend, and Explain: Advancing Conversational Recommender Systems with Large Language Model Agents | C13: Silva, Fillipe dos Santos | D13: 2025 | E13: Web of Science | F13: Primário | G13: 10.1145/3699682.3727569 | H13: https://doi.org/10.1145/3699682.3727569 | I13: From personalized shopping assistants to streaming service recommendations, Conversational Recommender Systems (CRSs) have become essential tools for decision-making. However, users often struggle to understand why particular items are recommended, leading to reduced trust, lower engagement, and less effective decisionmaking. At the same time, CRSs usually face challenges in recommendation accuracy as they struggle to integrate historical data, real-time feedback, and contextual signals effectively. This combination of unclear explanations and suboptimal recommendations diminishes user experience and system reliability. To address these challenges, we explore three key questions: (i) how the integration of structured and unstructured data can enhance downstream tasks in a Multi-Agent System (MAS)-based CRS architecture, (ii) how a MAS can generate dynamic and user-centric explanations, and (iii) how cross-agent collaboration can optimize recommendation accuracy. MAS-based architectures distribute critical tasks such as decision-making, data retrieval, optimization, and reasoning across specialized agents. A meta-agent oversees these agents, ensuring coordination and adaptability. This research aims to enhance the clarity of explanations and improve recommendation accuracy by integrating modular agents in a coordinated MAS framework, providing more personalized explanations and adapting to evolving user preferences. | J13: Sim | K13: RQ1; RQ2; RQ4; RQ5 | L13: Confirma aderência temática ao escopo MAS–LLM no título/resumo. Registro sem duplicidade aparente no conjunto consolidado.
A14: P-WOS-010 | B14: CCMA: A framework for cascading cooperative multi-agent in autonomous driving merging using Large Language Models | C14: Zhang, Miao; Fang, Zhenlong; Wang, Tianyi; Lu, Shuai; Wang, Xueqian; Shi, Tianyu | D14: 2025 | E14: Web of Science | F14: Primário | G14: 10.1016/j.eswa.2025.127717 | H14: https://doi.org/10.1016/j.eswa.2025.127717 | I14: Traditional Reinforcement Learning (RL) suffers from challenges in replicating human-like behaviors, generalizing effectively in multi-agent scenarios, and overcoming inherent interpretability issues. These tasks become even more difficult when they require a deep understanding of the environment, coordination of agents' intentions and driving styles across various scenarios, and the overall optimization of safety, efficiency, and comfort in dynamic environments. Recently, Large Language Model (LLM) enhanced methods have shown promise in improving generalization and interoperability. However, these approaches primarily focus on single-agent scenarios and often neglect the necessary coordination among multiple road users. Therefore, in this paper, we introduce the Cascading Cooperative Multi-agent (CCMA) framework, designed to address these challenges by enhancing human-like behaviors and fostering multi-level cooperation across diverse multi-agent driving tasks, ultimately improving both micro and macro-level performance in complex driving environments. Specifically, the CCMA framework integrates RL for individual interactions, a fine-tuned LLM for regional cooperation, a reward function for global optimization, and the Retrieval-augmented Generation mechanism to dynamically optimize decision-making across complex driving scenarios. Our experiments demonstrate that our CCMA method not only enhances human-like behaviors and interpretability, but also outperforms other state-of-the-art RL methods in multi-agent environments. These findings highlight the significant impact of cascading coordinated communication and dynamic functional alignment in advanced, human-like multi-agent autonomous driving environments. Our project page is https://miaorain.github.io/rainrun.github.io/. | J14: Sim | K14: RQ1; RQ2; RQ4; RQ5 | L14: Confirma aderência temática ao escopo MAS–LLM no título/resumo. Registro sem duplicidade aparente no conjunto consolidado.
A15: P-WOS-011 | B15: Privacy-by-Design in AI-Assisted Systems for Caregivers of Children with Autism: A Secure Multi-Agent Architecture | C15: Croitoru, Ionut; Turcu, Cristina Elena; Turcu, Corneliu Octavian | D15: 2026 | E15: Web of Science | F15: Primário | G15: 10.3390/app16042157 | H15: https://doi.org/10.3390/app16042157 | I15: Caregivers of children with Autism Spectrum Disorder (ASD) frequently experience chronic psychological stress, thereby necessitating accessible support. Although artificial intelligence (AI)-based assisted technologies have the potential to reduce caregiver workload, most existing solutions lack robust privacy control and clinical interoperability, which significantly limits their adoption in regulated healthcare environments. To address these challenges, this paper proposes a Privacy-by-Design (PbD) multi-agent architecture that enables consent-aware, auditable, and privacy-preserving AI-assisted support for caregivers of children with ASD. The effectiveness of the proposed architecture was evaluated using two datasets: one focusing on clinically grounded autism-related knowledge and another reflecting naturalistic caregiver observation language. System performance was assessed using a Retrieval-Augmented Generation Assessment (RAGAs)-based framework with a Large Language Model (LLM)-as-a-Judge approach implemented via a locally deployed Llama 3 8B model. The system achieved answer relevancy scores of 0.767 for the clinical dataset and 0.750 for the observational dataset, with corresponding Recall@K values of 0.400 and 0.742, respectively. Context precision ranged from 0.599 to 0.631, and no harmful content was detected. Overall, the proposed architecture demonstrates secure caregiver-specialist collaboration through consent-aware routing, anonymised data storage, and controlled data reconstruction, providing a regulation-aligned design option for privacy-preserving AI integration in assisted care platforms. | J15: Sim | K15: RQ1; RQ4; RQ5 | L15: Confirma aderência temática ao escopo MAS–LLM no título/resumo. Registro sem duplicidade aparente no conjunto consolidado.
A16: P-WOS-012 | B16: Multi-Agent Multimodal Large Language Model Framework for Automated Interpretation of Fuel Efficiency Analytics in Public Transportation | C16: Ma, Zhipeng; Bahja, Ali Rida; Burgdorf, Andreas; Pomp, Andre; Meisen, Tobias; Jorgensen, Bo Norregaard; Ma, Zheng Grace | D16: 2025 | E16: Web of Science | F16: Primário | G16: 10.3390/app152111619 | H16: https://doi.org/10.3390/app152111619 | I16: Enhancing fuel efficiency in public transportation requires the integration of complex multimodal data into interpretable, decision-relevant insights. However, traditional analytics and visualization methods often yield fragmented outputs that demand extensive human interpretation, limiting scalability and consistency. This study presents a multi-agent framework that leverages multimodal large language models (LLMs) to automate data narration and energy insight generation. The framework coordinates three specialized agents, including a data narration agent, an LLM-as-a-judge agent, and an optional human-in-the-loop evaluator, to iteratively transform analytical artifacts into coherent, stakeholder-oriented reports. The system is validated through a real-world case study on public bus transportation in Northern Jutland, Denmark, where fuel efficiency data from 4006 trips are analyzed using Gaussian Mixture Model clustering. Comparative experiments across five state-of-the-art LLMs and three prompting paradigms identify GPT-4.1 mini with Chain-of-Thought prompting as the optimal configuration, achieving 97.3\% narrative accuracy while balancing interpretability and computational cost. The findings demonstrate that multi-agent orchestration significantly enhances factual precision, coherence, and scalability in LLM-based reporting. The proposed framework establishes a replicable and domain-adaptive methodology for AI-driven narrative generation and decision support in energy informatics. | J16: Sim | K16: RQ1; RQ4; RQ5 | L16: Confirma aderência temática ao escopo MAS–LLM no título/resumo. Registro sem duplicidade aparente no conjunto consolidado.
... A89: P-WOS-085 | B89: Norm Violation Detection in Multi-Agent Systems Using Large Language Models A Pilot Study | C89: He, Shawn; Ranathunga, Surangika; Cranefield, Stephen; Savarimuthu, Bastin Tony Roy | D89: 2025 | E89: Web of Science | F89: Primário | G89: 10.1007/978-3-031-82039-7\_10 | H89: https://doi.org/10.1007/978-3-031-82039-7\_10 | I89: Norms are an important component of the social fabric of society by prescribing expected behaviour. In Multi-Agent Systems (MAS), agents interacting within a society are equipped to possess social capabilities such as reasoning about norms and trust. Norms have long been of interest within the Normative Multi-Agent Systems community with researchers studying topics such as norm emergence, norm violation detection and sanctioning. However, these studies have some limitations: they are often limited to simple domains, norms have been represented using a variety of representations with no standard approach emerging, and the symbolic reasoning mechanisms generally used may suffer from a lack of extensibility and robustness. In contrast, Large Language Models (LLMs) offer opportunities to discover and reason about norms across a large range of social situations. This paper evaluates the capability of LLMs to detecting norm violations. Based on simulated data from 80 stories in a household context, with varying complexities, we investigated whether 10 norms are violated. For our evaluations we first obtained the ground truth from three human evaluators for each story. Then, the majority result was compared against the results from three well-known LLM models (Llama 2 7B, Mixtral 7B and ChatGPT-4). Our results show the promise of ChatGPT-4 for detecting norm violations, with Mixtral some distance behind. Also, we identify areas where these models perform poorly and discuss implications for future work. | J89: Sim | K89: RQ3; RQ5; RQ6 | L89: Confirma aderência temática ao escopo MAS–LLM no título/resumo. Registro sem duplicidade aparente no conjunto consolidado.

Sheet IEEE - Estudos Secundários
A1: IEEE - Estudos Secundários
A2: Metadados organizados para rastreabilidade, auditoria e reprodução da RSL. Quantidade validada: 17 registros.
A4: ID do estudo | B4: Título | C4: Autores | D4: Ano | E4: Base de dados | F4: Tipo de estudo | G4: DOI | H4: Link | I4: Resumo | J4: Relevância para a pesquisa (Sim/Não) | K4: Questões de pesquisa atendidas (RQ1, RQ2, etc.) | L4: Observações
A5: S-IEEE-001 | B5: Are Autonomous Agents the Inevitable Future of Decentralized Finance? A Review and Forward Outlook | C5: S. N. Gularso; R. Wiputra | D5: 2025 | E5: IEEE Xplore | F5: Secundário | G5: 10.1109/IHMSC66529.2025.00038 | H5: https://ieeexplore.ieee.org/stamp/stamp.jsp?arnumber=11153232 | I5: Decentralized finance (DeFi) is expanding rapidly with the exponential increase in several adoption metrics. However, most user activity and decisions in DeFi still rely on short-term information, which exposes participants to volatility, manipulation, and security risk. Autonomous agents offer a data-driven approach to mitigate those frictions. This study conducts a systematic literature review (SLR) to map how LLM agents have been applied across the DeFi stack. We followed the PRISMA guidelines, searched five scholarly databases, and screened 3,590 records published between 2021 and 2025. Twenty-two peer-reviewed studies met the final inclusion criteria. Thematic synthesis reveals six functional clusters: (i) trading and automated market-making, (ii) portfolio construction and rebalancing, (iii) lending and credit-risk modeling, (iv) governance vote delegation, (v) liquidity-risk assurance and insurance, and (vi) smart-contract security audit. In terms of agent design, single-agent designs still dominate the implementation, but MAS is gaining traction in tasks requiring negotiation or distributed sensing. LLM-powered agents appear mainly in early proof-of-concept security tools. | J5: Sim | K5: RQ2; RQ5; RQ6 | L5: Confirma aderência temática ao escopo MAS–LLM no título/resumo. Registro sem duplicidade aparente no conjunto consolidado.
A6: S-IEEE-002 | B6: Agentic AI for Cloud Troubleshooting: A Review of Multi Agent System for Automated Cloud Support | C6: K. A. Patel; E. C. Pandey; I. Misra; D. Surve | D6: 2025 | E6: IEEE Xplore | F6: Secundário | G6: 10.1109/ICICT64420.2025.11005005 | H6: https://ieeexplore.ieee.org/stamp/stamp.jsp?arnumber=11005005 | I6: One of the growing approaches in the field of artificial intelligence is known as agentic AI. This term describes autonomous systems that are meant to pursue complicated goals with minimum interaction from humans. Agentic artificial intelligence displays flexibility, advanced decision-making capabilities, and self-sufficiency, which enables it to work dynamically in contexts that are constantly changing. This is in contrast to traditional artificial intelligence, which is dependent on inflexible instructions and tight oversight. An important step forward in artificial intelligence and contemporary software systems is represented by the development of agentic systems. This development is being pushed by the desire for vertical intelligence that is adapted to a variety of different sectors. Through their capacity for learning, flexibility, and interaction with dynamic settings, these systems improve the results of corporate operations. Large Language Model (LLM) agents, who constitute the cognitive backbone of modern intelligent systems, are at the vanguard of this transformation. They are the agents that are revolutionizing intelligent systems. The aim of this research is to create domain-specific agents to address cloud and SaaS troubleshooting concerns. A particular agent will be created for a designated cloud platform. Manage Personally Identifiable Information to hide data and improve user privacy. This review aims to discuss Agentic AI, its core components, and applications across industries. It also surveys the literature, explores solutions provided by Agentic AI for challenges related to cloud platform failures, examines LLMs as agentic workflows, analyzes the accuracy issues of large language models (LLMs), and presents the proposed methodology along with associated challenges. | J6: Não | K6: RQ4; RQ5 | L6: Sem evidência suficiente para confirmar aderência temática ao escopo MAS–LLM no título/resumo. Registro sem duplicidade aparente no conjunto consolidado.
A7: S-IEEE-003 | B7: Large Language Model Applications in Power Systems: A Comprehensive Review and Outlook | C7: X. Zhou; Y. Xu; J. Zhao; R. Zhang | D7: 2026 | E7: IEEE Xplore | F7: Secundário | G7: 10.35833/MPCE.2025.000760 | H7: https://ieeexplore.ieee.org/stamp/stamp.jsp?arnumber=11417457 | I7: Modern power systems are evolving due to increasing penetration of renewable energy sources, deeper participation of the demand side, and widespread deployment of advanced information and digital technologies. As a result, system operation and control are becoming increasingly challenging. Large language models (LLMs), with their advanced capabilities in semantic understanding and knowledge reasoning, offer a promising tool to support the operation, control, analysis, and decision-making of power systems. This paper provides a comprehensive review of LLM applications in power systems, encompassing four representative application domains: power grid, power equipment, demand side, and electricity market and policy-making. Based on the functional roles and implementations of LLMs, four major application strategies are identified—model adaptation, capability enhancement, multimodality integration, and multi-agent coordination. In addition, the core functions, representative methods, and evolving trends of LLM applications are reviewed across different domains. Finally, key challenges in applying LLMs to power systems are discussed, and future research directions are outlined with regard to ensuring physical feasibility, enhancing data efficiency and privacy, and improving interpretability and rationality. | J7: Sim | K7: RQ1; RQ2; RQ5; RQ6 | L7: Confirma aderência temática ao escopo MAS–LLM no título/resumo. Registro sem duplicidade aparente no conjunto consolidado.
A8: S-IEEE-004 | B8: TrustNet: A Hybrid Machine Learning and LLM-Based Multi-Agent System for Scam Website Detection | C8: S. Abdelhamid; J. Bangura; K. Redlinger; G. Romsland | D8: 2026 | E8: IEEE Xplore | F8: Secundário | G8: 10.1109/ICAIC67076.2026.11395765 | H8: https://ieeexplore.ieee.org/stamp/stamp.jsp?arnumber=11395765 | I8: The increase in the number of phishing and scam websites adds a continuous threat to online users. In this research, we present TrustNet, a hybrid AI platform that integrates traditional machine learning (ML) models with large language models (LLMs). We used different machine learning algorithms, and the Random Forest classifier achieved the highest performance, with an Accuracy of 0.9694, a Precision of 0.9749, a Recall of 0.9628, and an F1 of 0.9688. Further feature correlation and network centrality analyses showed the most influential attributes and their contribution to characterizing scam websites. Additionally, we built a multi-agent LLM system to identify and analyze linguistic and contextual indicators of scams in website content. The system contains four specialized agents (Market Researcher, Language Analyst, Threat Analyst, and Evaluator). The agents work together to identify urgency, vagueness, grammatical inconsistencies, and deceptive pressure tactics in web content. We tested the LLM-based agent system on our custom dataset of real and synthetic website text samples. The team of agents achieved high detection performance with an Accuracy of 0.9931, a Precision of 0.9867, a Recall of 1.0, and an F1 score of 0.9933. Both ML models and LLM-driven agents were integrated into a web-based application named TrustNet. TrustNet is a platform for detecting scams and phishing, and for explainable risk assessment. The system provides an interactive dashboard with risk-level visualization, linguistic explanation panels, and real-time recommendations to users. The proposed hybrid framework advances the state of the art in scam website detection by using both ML and LLM in a mixed approach that conducts both quantitative URL analysis and qualitative linguistic, contextual, and semantic knowledge extraction. | J8: Sim | K8: RQ1; RQ4; RQ5 | L8: Confirma aderência temática ao escopo MAS–LLM no título/resumo. Registro sem duplicidade aparente no conjunto consolidado.
A9: S-IEEE-005 | B9: Analysing the Role of Multi-Agent AI Models for Autonomous Business Decision Systems | C9: C. Tayal; S. Murumkar; S. Biradar | D9: 2026 | E9: IEEE Xplore | F9: Secundário | G9: 10.1109/CCWC67433.2026.11393746 | H9: https://ieeexplore.ieee.org/stamp/stamp.jsp?arnumber=11393746 | I9: The autonomous business decision systems are now the centre of organisational competitiveness as organisations continue to work in volatile and increasingly data-intensive and interdependent environments. The use of multi-agent systems (MAS) can provide an effective paradigm, which facilitates decentralised, adaptive and collaborative intelligence with distributed agents perceiving environments and negotiating actions and autonomous optimisation. This paper is a critical assessment of how multi-agent AI models, such as logic agents, multi-agent reinforcement learning (MARL), agents based on large language models, agent development systems, simulation systems, and self-evolving agents' systems, have contributed to autonomous business decision systems. Systematic literature reviews, simulations, enterprise case studies and foundation-model based research and decision intelligence (DI) frameworks evidence shows how multi agent strategies provides increased robustness, scalability and responsiveness to the complex organisational domains. Simulation-based research using MAS is seen to be able to model emerging behaviours, test organisational conditions and uncertainty within energy system, construction, logistics and financial fields. The further reinforcement learning and cooperative decision modelling enhance MAS autonomy as it provides the ability to optimise the learning of dynamic environments. Similar results are presented by the research of Automated Machine Learning (AutoML) that demonstrates that automated model development helps lower technical barriers and speeds up its deployment and enables adaptive decision pipelines. Decision Intelligence literature displays how organisations can restructure decision-making with the help of AI to construct data pipelines, and provide human-computer interaction. Although issues remain, such as explainability, cost of coordination and data governance, there is strong evidence that MAS constitute a backbone architecture to next generation autonomous decision ecosystems according to all sources. The given synthesis illustrates how multi-agent AI may be used as a strategic foundation of predictive, operational and strategic automation of decisions in contemporary businesses. | J9: Sim | K9: RQ2; RQ4; RQ5 | L9: Confirma aderência temática ao escopo MAS–LLM no título/resumo. Registro também identificado em outra base ou categoria de busca.
A10: S-IEEE-006 | B10: Hydra-Reviewer: A Holistic Multi-Agent System for Automatic Code Review Comment Generation | C10: X. Ren; C. Dai; Q. Huang; Y. Wang; C. Liu; B. Jiang | D10: 2025 | E10: IEEE Xplore | F10: Secundário | G10: 10.1109/TSE.2025.3621462 | H10: https://ieeexplore.ieee.org/stamp/stamp.jsp?arnumber=11203269 | I10: Review comment generation is a crucial task in code review, and significant progress has been made in automating. Previous research has generated review comments by fine-tuning pre-trained models or Large Language Models (LLMs). However, these studies have overlooked the necessity of conducting code reviews from multiple perspectives, resulting in the omission of potential issues in code changes. Additionally, the complexity of review comments often hinders the accurate quantitative evaluation of automated tools’ effectiveness. In this paper, we first conduct an empirical study to propose a comprehensive taxonomy of code review dimensions. We also identify three major limitations of existing automated code review (ACR) methods: lack of comprehensiveness, incorrectness, and vagueness. Building on the insights from our empirical study, we introduce Hydra-Reviewer, a collaborative multi-agent framework powered by large language models, designed to automatically generate high-quality code reviews. We utilize the CodeReview and CodeReviewNew benchmark datasets, along with a newly constructed review comment generation dataset. We compare Hydra-Reviewer with several baselines, including CodeReviewer, LLaMA-Reviewer, ChatGPT, Comprehensive-ChatGPT, and DeepSeek-V3. The experimental results show that Hydra-Reviewer achieves a BLEU score of 8.20, outperforming the state-of-the-art baseline, DeepSeek-V3, which scores 7.85. In qualitative evaluation, Hydra-Reviewer’s generated comments span an average of 7.8 review dimensions, addressing the limitations of existing ACR methods effectively. Additionally, Hydra-Reviewer demonstrates strong generalization capabilities on unseen dataset. We further validate the contributions of each component of Hydra-Reviewer through an ablation study and confirm the helpfulness and readability of the generated comments via a User Study. Finally, a cost analysis reveals that Hydra-Reviewer generates review comments at an average cost of 0.018 dollars and 62.63 seconds per code change. | J10: Sim | K10: RQ4; RQ5 | L10: Confirma aderência temática ao escopo MAS–LLM no título/resumo. Registro também identificado em outra base ou categoria de busca.
A11: S-IEEE-007 | B11: Can Large Language Models Be Trusted Paper Reviewers? A Feasibility Study | C11: C. Li; X. Hu; M. Xu; K. Li; Y. Zhang; X. Cheng | D11: 2025 | E11: IEEE Xplore | F11: Secundário | G11: 10.1109/MASS66014.2025.00086 | H11: https://ieeexplore.ieee.org/stamp/stamp.jsp?arnumber=11206164 | I11: Academic paper review typically requires substantial time, expertise, and human resources. Large Language Models (LLMs) present a promising method for automating the review process due to their extensive training data, broad knowledge base, and relatively low usage cost. This work explores the feasibility of using LLMs for academic paper review by proposing an automated review system. The system integrates Retrieval Augmented Generation (RAG), the AutoGen multi-agent system, and Chain-of-Thought prompting to support tasks such as format checking, standardized evaluation, comment generation, and scoring. Experiments conducted on 290 submissions from the WASA 2024 conference using GPT-4o show that LLM-based review significantly reduces review time (average 2.48 hours) and cost (average $104.28 USD). However, the similarity between LLM-selected papers and actual accepted papers remains low (average 38.6%), indicating issues such as hallucination, lack of independent judgment, and retrieval preferences. Therefore, it is recommended to use LLMs as assistive tools to support human reviewers, rather than to replace them. | J11: Sim | K11: RQ4 | L11: Confirma aderência temática ao escopo MAS–LLM no título/resumo. Registro sem duplicidade aparente no conjunto consolidado.
A12: S-IEEE-008 | B12: LABMATE: Language Model Based Multi-Agent System to Accelerate Catalysis Experiments | C12: A. Acharya; A. K. Sharma; D. Parker; T. Vega; R. A. Ashraf; N. M. Isenberg; J. Strube; R. Rallo | D12: 2025 | E12: IEEE Xplore | F12: Secundário | G12: Não informado | H12: https://ieeexplore.ieee.org/stamp/stamp.jsp?arnumber=11358161 | I12: As Large Language Models (LLMs) have become increasingly commonplace, they have been shown to be useful to domains far beyond just linguistic tasks. However, they are still unreliable to make decisions due to their potential to hallucinate, and unable to perform complex tasks like running simulations that are essential to a field like Material Science. To solve this, we introduce LABMATE (LAnguage model Based Multi-agent system to Accelerate caTalysis Experiments), a human-in-the-loop copilot framework that utilizes LLM agents to make catalysis research faster. LABMATE allows the human experts to submit simulation runs, track particle sizes, run data analysis, perform literature review, and generate potential hypothesis all in one framework, thereby expediting the research process. When evaluated on the Chemistry and Material Science segments of major benchmarks, LABMATE performs comparable to or better than most frontier LLMs, showing that in addition to accelerating the experimental process, our framework is also on par in domain knowledge compared to using a simple LLM. These results show that the system is able to significantly aid and improve the research process for human scientists. Furthermore, since the core architecture of the system is domain-agnostic, it can easily be adapted to other domains. | J12: Sim | K12: RQ4 | L12: Confirma aderência temática ao escopo MAS–LLM no título/resumo. Registro sem duplicidade aparente no conjunto consolidado.
A13: S-IEEE-009 | B13: Using Role-Specialized LLM Agents for Workflow Execution in a Product Development Setting | C13: M. Kretzschmar; A. Gundermann; J. Mehlstäubl; A. P. Gómez; B. Saske; K. Paetzold-Byhain | D13: 2025 | E13: IEEE Xplore | F13: Secundário | G13: 10.1109/ICISC65841.2025.11188152 | H13: https://ieeexplore.ieee.org/stamp/stamp.jsp?arnumber=11188152 | I13: Many product development tasks require multi-step reasoning and decision-making that exceed the capabilities of Large Language Models (LLMs) operating in isolation. This research introduces a framework for constructing multi-agent systems (MAS) with LLMs for product development and presents an empirical study of its effectiveness. By decomposing workflows into subtasks handled by role-specialized agents, the system leverages agentic design principles and outperforms isolated model outputs. We evaluate this approach using LLaMA-3.1 (8B) and Gemma 2.0 (9B) in a realistic engineering scenario. While enabling more complex problem solving, the MAS also introduces challenges in transparency and fault tracing across input-output chains. Our findings highlight trade-offs and the need for further research on design practices for reliable agentic AI systems in industrial settings. | J13: Sim | K13: RQ4; RQ5 | L13: Confirma aderência temática ao escopo MAS–LLM no título/resumo. Registro também identificado em outra base ou categoria de busca.
A14: S-IEEE-010 | B14: Agentic AI Approaches for Indian Medicinal Plant Knowledge Systems | C14: P. Honna; S. Chand; N. D. Rangdal; A. Patravali; R. M S; R. S | D14: 2025 | E14: IEEE Xplore | F14: Secundário | G14: 10.1109/CSITSS67709.2025.11295437 | H14: https://ieeexplore.ieee.org/stamp/stamp.jsp?arnumber=11295437 | I14: The fusion of Artificial Intelligence (AI) with traditional knowledge systems presents a promising direction for preserving and expanding access to India's rich medicinal plant heritage. Agentic AI, defined by autonomous reasoning, iterative planning, and adaptive problem solving, serves as a powerful tool for digitizing, analyzing, and sharing indigenous knowledge related to medicinal plants. This survey investigates the use of Natural Language Processing (NLP), Machine Learning (ML), Large Language Models (LLM), Retrieval Augmented Generation (RAG), and Question Answering (QA) techniques in the development of intelligent systems for Indian medicinal plant knowledge. Current frameworks and successful applications in healthcare and ethnobotany are reviewed, alongside the integration challenges posed by diverse data sources and traditional wisdom. Evaluation of a single RAG based agent demonstrated high effectiveness, achieving a precision of 88.48%, recall of 88.64%, and $F 1$ score of 88.56%. In comparison, a standalone LLM achieved a precision of 80.41%, recall of 85.56%, and F1 score of 82.90%. These results reflect the potential of agentic AI to bridge ancient practices and modern science, offering actionable and context aware insights to support sustainable healthcare and biodiversity management. | J14: Não | K14: RQ1; RQ5 | L14: Sem evidência suficiente para confirmar aderência temática ao escopo MAS–LLM no título/resumo. Registro sem duplicidade aparente no conjunto consolidado.
A15: S-IEEE-011 | B15: A Survey on Agent Workflow – Status and Future | C15: C. Yu; Z. Cheng; H. Cui; Y. Gao; Z. Luo; Y. Wang; H. Zheng; Y. Zhao | D15: 2025 | E15: IEEE Xplore | F15: Secundário | G15: 10.1109/ICAIBD64986.2025.11082076 | H15: https://ieeexplore.ieee.org/stamp/stamp.jsp?arnumber=11082076 | I15: In the age of large language models (LLMs), autonomous agents have emerged as a powerful paradigm for achieving general intelligence. These agents dynamically leverage tools, memory, and reasoning capabilities to accomplish user-defined goals. As agent systems grow in complexity, agent workflows—structured orchestration frameworks have become central to enabling scalable, controllable, and secure AI behaviors. This survey provides a comprehensive review of agent workflow systems, spanning academic frameworks and industrial implementations. We classify existing systems along two key dimensions: functional capabilities (e.g., planning, multi-agent collaboration, external API integration) and architectural features (e.g., agent roles, orchestration flows, specification languages). By comparing over 20 representative systems, we highlight common patterns, potential technical challenges, and emerging trends. We further address concerns related to workflow optimization strategies and security. Finally, we outline open problems such as standardization, and multi-modal integration—offering insights for future research at the intersection of agent design, workflow infrastructure, and safe automation. | J15: Sim | K15: RQ1; RQ3; RQ4; RQ5; RQ6 | L15: Confirma aderência temática ao escopo MAS–LLM no título/resumo. Registro sem duplicidade aparente no conjunto consolidado.
A16: S-IEEE-012 | B16: LLM-Based Multi-Agent Decision-Making: Challenges and Future Directions | C16: C. Sun; S. Huang; D. Pompili | D16: 2025 | E16: IEEE Xplore | F16: Secundário | G16: 10.1109/LRA.2025.3562371 | H16: https://ieeexplore.ieee.org/stamp/stamp.jsp?arnumber=10970024 | I16: In recent years, Large Language Models (LLMs) have shown great abilities in various tasks, including question answering, arithmetic problem solving, and poetry writing, among others. Although research on LLM-as-an-agent has shown that LLM can be applied to Decision-Making (DM) and achieve decent results, the extension of LLM-based agents to Multi-Agent DM (MADM) is not trivial, as many aspects, such as coordination and communication between agents, are not considered in the DM frameworks of a single agent. To inspire more research on LLM-based MADM, in this letter, we survey the existing LLM-based single-agent and multi-agent decision-making frameworks and provide potential research directions for future research. In particular, we focus on the cooperative tasks of multiple agents with a common goal and communication among them. We also consider human-in/on-the-loop scenarios enabled by the language component in the framework. | J16: Sim | K16: RQ2; RQ4; RQ5; RQ6 | L16: Confirma aderência temática ao escopo MAS–LLM no título/resumo. Registro também identificado em outra base ou categoria de busca.
... A21: S-IEEE-017 | B21: Empowering Conversational Systems Through AI Agents Specialized in Reusable APIs Across Software Ecosystems | C21: R. R. Lima; I. E. C. de Brito; J. da Cunha Nascimento; E. N. Nogueira | D21: 2025 | E21: IEEE Xplore | F21: Secundário | G21: 10.1109/ICTAI66417.2025.00191 | H21: https://ieeexplore.ieee.org/stamp/stamp.jsp?arnumber=11272526 | I21: Software reuse is a key strategy in modern engineering practices, yet it remains underexploited in enterprise environments due to technical barriers and limited accessibility to existing functionalities. This paper presents a novel architecture that integrates LLMs with AI agents to enhance conversational systems, enabling intelligent reuse of enterprise APIs through natural language commands. To test the feasibility of this solution, a multi-agent system with three roles was designed - LLM interpreter, recommender agent, and executor agent - deployed in a real-world setting. The solution evaluation combined automated accuracy tests, a TAM-based user satisfaction survey, and focus groups with developers. The bge-m3 embedding model achieved the highest top-5 recommendation accuracy. Users reported increased perceived usefulness and ease of use. Developers valued the modularity of the architecture, but expressed concerns about operational risks. The proposed architecture effectively connects user intent to actionable enterprise APIs, enhancing reuse, accessibility, and adaptability while pointing to future improvements in security, learning, and transparency. | J21: Sim | K21: RQ4; RQ5 | L21: Confirma aderência temática ao escopo MAS–LLM no título/resumo. Registro sem duplicidade aparente no conjunto consolidado.

Sheet ACM - Estudos Secundários
A1: ACM - Estudos Secundários
A2: Metadados organizados para rastreabilidade, auditoria e reprodução da RSL. Quantidade validada: 75 registros.
A4: ID do estudo | B4: Título | C4: Autores | D4: Ano | E4: Base de dados | F4: Tipo de estudo | G4: DOI | H4: Link | I4: Resumo | J4: Relevância para a pesquisa (Sim/Não) | K4: Questões de pesquisa atendidas (RQ1, RQ2, etc.) | L4: Observações
A5: S-ACM-001 | B5: Large Language Models for Cyber Security: A Systematic Literature Review | C5: Xu, Hanxiang; Wang, Shenao; Li, Ningke; Wang, Kailong; Zhao, Yanjie; Chen, Kai; Yu, Ting; Liu, Yang; Wang, Haoyu | D5: 2025 | E5: ACM Digital Library | F5: Secundário | G5: 10.1145/3769676 | H5: https://doi.org/10.1145/3769676 | I5: The rapid advancement of Large Language Models (LLMs) has opened up new opportunities for leveraging artificial intelligence in a variety of application domains, including cybersecurity. As the volume and sophistication of cyber threats continue to grow, there is an increasing need for intelligent systems that can automatically detect vulnerabilities, analyze malware, and respond to attacks. In this survey, we conduct a comprehensive review of the literature on the application of LLMs in cybersecurity (LLM4Security). By comprehensively collecting over 40K relevant papers and systematically analyzing 185 papers from top security and software engineering venues, we aim to provide a holistic view of how LLMs are being used to solve diverse problems across the cybersecurity domain.Through our analysis, we identify several key findings. First, we observe that LLMs are being applied to an expanding range of cybersecurity tasks, including vulnerability detection, malware analysis, and network intrusion detection. Second, we analyze application trends of different LLM architectures (such as encoder-only, encoder-decoder, and decoder-only) across security domains. Third, we identify increasingly sophisticated techniques for adapting LLMs to cybersecurity, such as advanced fine-tuning, prompt engineering, and external augmentation strategies. A significant emerging trend is the use of LLM-based autonomous agents, which represent a paradigm shift from single-task execution to orchestrating complex, multi-step security workflows. Furthermore, we find that the datasets used for training and evaluating LLMs are often limited, highlighting the need for more comprehensive datasets and the use of LLMs for data augmentation. Finally, we discuss the main challenges and opportunities for future research, including the need for more interpretable models, addressing the inherent security risks of LLMs, and their potential for proactive defense.Overall, our survey provides a comprehensive overview of the current state-of-the-art in LLM4Security and identifies several promising directions for future research. We believe that the insights and findings presented in this survey will contribute to the growing body of knowledge on the application of LLMs in cybersecurity and provide valuable guidance for researchers and practitioners working in this field. | J5: Não | K5: RQ5; RQ6 | L5: Sem evidência suficiente para confirmar aderência temática ao escopo MAS–LLM no título/resumo. Registro também identificado em outra base ou categoria de busca.
A6: S-ACM-002 | B6: Large Language Model-Based Agents for Software Engineering: A Survey | C6: Liu, Junwei; Wang, Kaixin; Chen, Yixuan; Peng, Xin; Chen, Zhenpeng; Zhang, Lingming; Lou, Yiling | D6: 2026 | E6: ACM Digital Library | F6: Secundário | G6: 10.1145/3796507 | H6: https://doi.org/10.1145/3796507 | I6: The recent advance in Large Language Models (LLMs) has shaped a new paradigm of AI agents, i.e., LLM-based agents. Compared to standalone LLMs, LLM-based agents substantially extend the versatility and expertise of LLMs by enhancing LLMs with the capabilities of perceiving and utilizing external resources and tools. To date, LLM-based agents have been applied and shown remarkable effectiveness in Software Engineering (SE). The synergy between multiple agents and human interaction brings further promise in tackling complex real-world SE problems. In this work, we present a comprehensive and systematic survey on LLM-based agents for SE. We collect 124 papers and categorize them from two perspectives, i.e., the SE and agent perspectives. In addition, we discuss open challenges and future directions in this critical domain. The repository of this survey is at . | J6: Não | K6: RQ5; RQ6 | L6: Sem evidência suficiente para confirmar aderência temática ao escopo MAS–LLM no título/resumo. Registro também identificado em outra base ou categoria de busca.
A7: S-ACM-003 | B7: A Survey on the Memory Mechanism of Large Language Model-based Agents | C7: Zhang, Zeyu; Dai, Quanyu; Bo, Xiaohe; Ma, Chen; Li, Rui; Chen, Xu; Zhu, Jieming; Dong, Zhenhua; Wen, Ji-Rong | D7: 2025 | E7: ACM Digital Library | F7: Secundário | G7: 10.1145/3748302 | H7: https://doi.org/10.1145/3748302 | I7: Large language model (LLM)-based agents have recently attracted much attention from the research and industry communities. Compared with original LLMs, LLM-based agents are featured in their self-evolving capability, which is the basis for solving real-world problems that need long-term and complex agent-environment interactions. The key component to support agent-environment interactions is the memory of the agents. While previous studies have proposed many promising memory mechanisms, they are scattered in different papers, and there lacks a systematical review to summarize and compare these works from a holistic perspective, failing to abstract common and effective designing patterns for inspiring future studies. To bridge this gap, in this article, we propose a comprehensive survey on the memory mechanism of LLM-based agents. In specific, we first discuss “what is” and “why do we need” the memory in LLM-based agents. Then, we systematically review previous studies on how to design and evaluate the memory module. In addition, we also present many agent applications, where the memory module plays an important role. At last, we analyze the limitations of existing work and show important future directions. To keep up with the latest advances in this field, we create a repository at . | J7: Não | K7: RQ5; RQ6 | L7: Sem evidência suficiente para confirmar aderência temática ao escopo MAS–LLM no título/resumo. Registro também identificado em outra base ou categoria de busca.
A8: S-ACM-004 | B8: A Survey on the Optimization of Large Language Model-based Agents | C8: Du, Shangheng; Zhao, Jiabao; Shi, Jinxin; Xie, Zhentao; Jiang, Xin; Bai, Yanhong; He, Liang | D8: 2026 | E8: ACM Digital Library | F8: Secundário | G8: 10.1145/3789261 | H8: https://doi.org/10.1145/3789261 | I8: With the rapid development of Large Language Models (LLMs), LLM-based agents have been widely adopted in various fields, becoming essential for autonomous decision-making and interactive tasks. However, current work typically relies on prompt design or fine-tuning strategies applied to vanilla LLMs, which often leads to limited effectiveness in complex agent-related environments. Although numerous recent studies have explored various strategies to optimize LLM-based agents for complex agent tasks, a systematic review summarizing and comparing these methods from a holistic perspective remains lacking. In this survey, we provide a comprehensive review of LLM-based agent optimization approaches, categorizing them into parameter-driven and parameter-free methods. We first focus on parameter-driven optimization, covering fine-tuning-based optimization, reinforcement learning-based optimization, and hybrid strategies, analyzing key aspects such as trajectory data construction, reward function design, and optimization algorithms. Additionally, we briefly discuss parameter-free strategies that optimize agent behavior through prompt engineering and external knowledge retrieval. Finally, we summarize the evaluation for agents, review key applications of LLM-based agents, and discuss the major challenges and promising future directions. A curated collection of the surveyed works is provided at https://github.com/YoungDubbyDu/LLM-Agent-Optimization. | J8: Não | K8: RQ5; RQ6 | L8: Sem evidência suficiente para confirmar aderência temática ao escopo MAS–LLM no título/resumo. Registro também identificado em outra base ou categoria de busca.
A9: S-ACM-005 | B9: ModelGen: Automating Semiconductor Parameter Extraction with Large Language Model Agents | C9: Wei, Yangbo; Huang, Li; Feng, Qi; Chen, Zhanfei; Yan, Jinlong; Lin, Ting-Jung; Huang, Zhen; Ren, Kun; Xing, Wei; He, Lei | D9: 2025 | E9: ACM Digital Library | F9: Secundário | G9: 10.1145/3736165 | H9: https://doi.org/10.1145/3736165 | I9: Device models require large numbers of parameters to characterize complex physical effects. Although the latest advancements in machine learning and automated tools have drastically improved efficiency over the classic methods, they still demand a considerable amount of human intervention in the loop to gain accuracy. This drastically limits further automation. Inspired by the success of Multimodal Large Language Models (MLLMs) in addressing tasks across diverse fields, we propose ModelGen, the first in-depth study to leverage MLLMs with RAG (Retrieval-Augmented Generation) to significantly reduce human effort in parameter extraction for compact model. Our contributions include (1) Automated Agentic Workflow Construction that learns to build and refine extraction workflows through iterative optimization, (2) MLLM Judge, a visual scoring mechanism that evaluates fitting quality using actual device characteristic plots rather than simple numerical metrics, and (3) Model-specific RAG for providing relevant domain knowledge during the extraction process. Experimental results demonstrate that ModelGen achieves a 26.8%–33.1% improvement in pass@1,3,5 compared to base LLM methods. The system completes complex model extractions for BSIMs and ASM-HEMT in hours (up to 168\texttimes{} faster) rather than days or weeks, making parameter extraction more accessible to non-experts while maintaining professional engineer-level accuracy. | J9: Não | K9: Não identificado | L9: Sem evidência suficiente para confirmar aderência temática ao escopo MAS–LLM no título/resumo. Registro também identificado em outra base ou categoria de busca.
A10: S-ACM-006 | B10: MetaAgents: Large Language Model Based Agents for Decision-Making on Teaming | C10: Li, Yuan; Sun, Lichao; Zhang, Yixuan | D10: 2025 | E10: ACM Digital Library | F10: Secundário | G10: 10.1145/3711032 | H10: https://doi.org/10.1145/3711032 | I10: Significant advancements have occurred in the application of Large Language Models (LLMs) for social simulations. Despite this, their abilities to perform teaming in task-oriented social events are underexplored. Such capabilities are crucial if LLMs are to effectively mimic human-like social behaviors and form efficient teams to solve tasks. To bridge this gap, we introduce MetaAgents, a social simulation framework populated with LLM-based agents. MetaAgents facilitates agent engagement in conversations and a series of decision making within social contexts, serving as an appropriate platform for investigating interactions and interpersonal decision-making of agents. In particular, we construct a job fair environment as a case study to scrutinize the team assembly and skill-matching behaviors of LLM-based agents. We take advantage of both quantitative metrics evaluation and qualitative text analysis to assess their teaming abilities at the job fair. Our evaluation demonstrates that LLM-based agents perform competently in making rational decisions to develop efficient teams. However, we also identify limitations that hinder their effectiveness in more complex team assembly tasks. Our work provides valuable insights into the role and evolution of LLMs in task-oriented social simulations. | J10: Não | K10: RQ4; RQ5 | L10: Sem evidência suficiente para confirmar aderência temática ao escopo MAS–LLM no título/resumo. Registro também identificado em outra base ou categoria de busca.
A11: S-ACM-007 | B11: The Emerged Security and Privacy of LLM Agent: A Survey with Case Studies | C11: He, Feng; Zhu, Tianqing; Ye, Dayong; Liu, Bo; Zhou, Wanlei; Yu, Philip S. | D11: 2025 | E11: ACM Digital Library | F11: Secundário | G11: 10.1145/3773080 | H11: https://doi.org/10.1145/3773080 | I11: Inspired by the rapid development of Large Language Models (LLMs), LLM agents have evolved to perform complex tasks. LLM agents are now extensively applied across various domains, handling vast amounts of data to interact with humans and execute tasks. The widespread applications of LLM agents demonstrate their significant commercial value; however, they also expose security and privacy vulnerabilities. At the current stage, comprehensive research on the security and privacy of LLM agents is highly needed. This survey aims to provide a comprehensive overview of the newly emerged privacy and security issues faced by LLM agents. We begin by introducing the fundamental knowledge of LLM agents, followed by a categorization and analysis of the threats. We then discuss the impacts of these threats on humans, environment, and other agents. Subsequently, we review existing defensive strategies, and finally explore future trends. Additionally, the survey incorporates diverse case studies to facilitate a more accessible understanding. By highlighting these critical security and privacy issues, the survey seeks to stimulate future research towards enhancing the security and privacy of LLM agents, thereby increasing their reliability and trustworthiness in future applications. | J11: Não | K11: RQ5; RQ6 | L11: Sem evidência suficiente para confirmar aderência temática ao escopo MAS–LLM no título/resumo. Registro também identificado em outra base ou categoria de busca.
A12: S-ACM-008 | B12: LLM-Based Multi-Agent Systems for Software Engineering: Literature Review, Vision, and the Road Ahead | C12: He, Junda; Treude, Christoph; Lo, David | D12: 2025 | E12: ACM Digital Library | F12: Secundário | G12: 10.1145/3712003 | H12: https://doi.org/10.1145/3712003 | I12: Integrating Large Language Models (LLMs) into autonomous agents marks a significant shift in the research landscape by offering cognitive abilities that are competitive with human planning and reasoning. This article explores the transformative potential of integrating Large Language Models into Multi-Agent (LMA) systems for addressing complex challenges in software engineering (SE). By leveraging the collaborative and specialized abilities of multiple agents, LMA systems enable autonomous problem-solving, improve robustness, and provide scalable solutions for managing the complexity of real-world software projects. In this article, we conduct a systematic review of recent primary studies to map the current landscape of LMA applications across various stages of the software development lifecycle (SDLC). To illustrate current capabilities and limitations, we perform two case studies to demonstrate the effectiveness of state-of-the-art LMA frameworks. Additionally, we identify critical research gaps and propose a comprehensive research agenda focused on enhancing individual agent capabilities and optimizing agent synergy. Our work outlines a forward-looking vision for developing fully autonomous, scalable, and trustworthy LMA systems, laying the foundation for the evolution of Software Engineering 2.0. | J12: Sim | K12: RQ5; RQ6 | L12: Confirma aderência temática ao escopo MAS–LLM no título/resumo. Registro também identificado em outra base ou categoria de busca.
A13: S-ACM-009 | B13: Extended Reality Cybersickness Assessment via User Review Analysis | C13: Li, Shuqing; Zheng, Qisheng; Gao, Cuiyun; Feng, Jia; Lyu, Michael R. | D13: 2025 | E13: ACM Digital Library | F13: Secundário | G13: 10.1145/3728933 | H13: https://doi.org/10.1145/3728933 | I13: In recent years, the extended reality (XR) software ecosystem has emerged as the next ubiquitous computing platform, as they provide users with immersive interactive experiences. However, XR ecosystem suffers from cybersickness problems, which would greatly affect user comfort and safety, leading to symptoms like headaches, disorientation, etc. That makes effective cybersickness assessment a timely and important question. The state-of-the-art methods of assessing the cybersickness of XR software typically monitor the biological metrics of users, during XR usage, which rely heavily on manual playtesting,sufferring from limited scalability issue. User reviews on XR app stores are informative for developers to learn the cybersickness ratings of their apps and the reasons behind. Nevertheless, the large number of user reviews can hardly be analyzed by developers manually, and most current automatic user review analysis methods can only provide coarse-grained or abstract results, such as extracting several high-level key topic groups discussed by reviews. Recent advancements in LLMs may bring new opportunities. However, directly leveraging LLMs for evaluating XR cybersickness is challenging because LLMs perform poorly on a large number of short texts, and their context window is limited. To address these challenges, we introduce XRCare, a comprehensive framework designed to automate the assessment of cybersickness and root cause reasoning for XR apps by resorting to fine-grained user review analysis. XRCare mainly includes three phases: (1) Insight pool construction, when XRCare collects the cybersickness analyzing chains and corresponding analyzing results from domain experts; (2) Reasoning graph construction, when XRCare dynamically extracts, categorizes, and maintains the reasons from user reviews that make users feel cybersickness on a self-evolving hierarchical graph; and (3) Multi-agent deductive cybersickness reasoning, which utilizes a multi-agent system to simulate diverse user demographics for analyzing and rating the intensity of cybersickness, as well as the causes of cybersickness. This structured approach allows XRCare to systematically identify, categorize, and address instances of cybersickness. For experiments, we construct a large-scale dataset consisting of 685,111 user reviews from 9,667 XR apps. Our evaluation shows that XRCare enhances the F1-score by 20.63% over the best-performing baseline and by 32.27% on average across all baselines, while also offering more accurate and detailed interpretability insights. | J13: Sim | K13: RQ4; RQ5 | L13: Confirma aderência temática ao escopo MAS–LLM no título/resumo. Registro também identificado em outra base ou categoria de busca.
A14: S-ACM-010 | B14: Fundamental Capabilities and Applications of Large Language Models: A Survey | C14: Li, Jiawei; Gao, Yang; Yang, Yizhe; Bai, Yu; Zhou, Xiaofeng; Li, Yinghao; Sun, Huashan; Liu, Yuhang; Si, Xingpeng; Ye, Yuhao; Wu, Yixiao; Lin, Yiguan; Xu, Bin; Ren, Bowen; Feng, Chong; Huang, Heyan | D14: 2025 | E14: ACM Digital Library | F14: Secundário | G14: 10.1145/3735632 | H14: https://doi.org/10.1145/3735632 | I14: Large Language Models (LLMs) have demonstrated remarkable effectiveness across various domain-specific applications. However, which fundamental capabilities most contribute to their success in different domains remains unclear. This uncertainty complicates LLM evaluation, as existing benchmark-based assessments often fail to capture their real-world performance, where the required capabilities may differ from those measured in the benchmarks. In this survey, we provide a systematic introduction to LLMs’ fundamental capabilities, encompassing their definitions, formation mechanisms, and practical applications. We further explore the relationships among these capabilities and discuss how they collectively support complex problem-solving in domain-specific applications. Building on this foundation, we review recent advances in LLM-driven applications across nine specific domains: medicine, law, computational biology, finance, social sciences and psychology, computer programming and software engineering, robots and agents, AI for disciplines, and creative work. We analyze how specific capabilities are leveraged for each domain to address unique requirements. This perspective enables us to establish connections between these capabilities and domain requirements, and to evaluate the varying importance of different capabilities across different domains. Based on these insights, we propose evaluation strategies tailored to the essential capabilities required in each domain, offering practical guidance for selecting suitable backbone LLMs in real-world applications. | J14: Não | K14: RQ5 | L14: Sem evidência suficiente para confirmar aderência temática ao escopo MAS–LLM no título/resumo. Registro também identificado em outra base ou categoria de busca.
A15: S-ACM-011 | B15: Integrating Various Software Artifacts for Better LLM-based Bug Localization and Program Repair | C15: Feng, Qiong; Ma, Xiaotian; Sheng, Jiayi; Feng, Ziyuan; Song, Wei; Liang, Peng | D15: 2025 | E15: ACM Digital Library | F15: Secundário | G15: 10.1145/3770581 | H15: https://doi.org/10.1145/3770581 | I15: LLMs have garnered considerable attention for their potential to streamline Automated Program Repair (APR). LLM-based approaches can either insert the correct code using an infilling-style technique or directly generate patches when provided with buggy methods, aiming for plausible patches to pass all tests. However, most of LLM-based APR methods rely on a single type of software information, such as issue descriptions or error stack traces, without fully leveraging a combination of diverse software artifacts. Human developers, in contrast, often use a range of information — such as debugging data, issue discussions, and error stack traces — to diagnose and fix bugs. Despite this, many LLM-based approaches do not explore which specific types of software information best assist in localizing and repairing software bugs. Addressing this gap is crucial for advancing LLM-based APR techniques.To investigate this and mimic the way human developers fix bugs, we propose DEVLoRe (short for DEVeloper Localization and Repair). In this framework, LLMs first use issue content (description and discussion) and stack error traces to localize buggy methods, then rely on debug information in buggy methods and issue content and stack error to localize buggy lines and generate valid patches. We evaluated the effectiveness of issue content, error stack traces, and debugging information in bug localization and automatic program repair. Our results show that while issue content and error stack is particularly effective in assisting LLMs with fault localization and program repair respectively, different types of software artifacts complement each other in addressing various bugs. By incorporating these three types of artifacts and using the Defects4J v2.0 dataset for evaluation, DEVLoRe successfully localizes 49.3% of single-method bugs and generates 56.0% plausible patches. Additionally, DEVLoRe can localize 47.6% of non-single-method bugs and generates 14.5% plausible patches. Moreover, our framework streamlines the end-to-end process from buggy source code to a complete repair, and achieves a 39.7% and 17.1% of single-method and non-single-method bug repair rate, outperforming current state-of-the-art APR methods. Furthermore, we re-implemented and evaluated our framework, demonstrating its effectiveness in resolving 9 unique issues compared to other state-of-the-art frameworks using the same or more advanced models on SWE-bench Lite. We also discussed whether a leading framework for Python code can be directly applied to Java code, or vice versa. The source code and experimental results of this work for replication are available at . | J15: Não | K15: RQ4 | L15: Sem evidência suficiente para confirmar aderência temática ao escopo MAS–LLM no título/resumo. Registro também identificado em outra base ou categoria de busca.
A16: S-ACM-012 | B16: LLMs May Not Be Human-Level Players, But They Can Be Testers: Measuring Game Difficulty with LLM Agents | C16: Xiao, Chang; Yang, Zixiaofan | D16: 2025 | E16: ACM Digital Library | F16: Secundário | G16: 10.1145/3748634 | H16: https://doi.org/10.1145/3748634 | I16: Recent advances in Large Language Models (LLMs) have demonstrated their potential as autonomous agents across various tasks. One emerging application is the use of LLMs in playing games. In this work, we explore a practical problem for the gaming industry: Can LLMs be used to measure game difficulty? We evaluate the feasibility of using LLM agents to test game difficulty, focusing on two widely played games: Wordle and Slay the Spire. Our results reveal an interesting finding: although LLMs may not perform as well as the average human player, their performance, when guided by simple, generic prompting techniques, shows a statistically significant and strong correlation with difficulty indicated by human players. This suggests that LLMs could potentially serve as human-like agents for measuring game difficulty during the development process, as their assessments may align closely with those of human players. Based on our experiments, we also propose general principles and guidelines for integrating LLMs into the game testing workflow. | J16: Não | K16: RQ5 | L16: Sem evidência suficiente para confirmar aderência temática ao escopo MAS–LLM no título/resumo. Registro também identificado em outra base ou categoria de busca.
... A79: S-ACM-075 | B79: Advantage of deep neural networks for estimating functions with singularity on hypersurfaces | C79: Imaizumi, Masaaki; Fukumizu, Kenji | D79: 2022 | E79: ACM Digital Library | F79: Secundário | G79: Não informado | H79: Não informado | I79: We develop a minimax rate analysis to describe the reason that deep neural networks (DNNs) perform better than other standard methods. For nonparametric regression problems, it is well known that many standard methods attain the minimax optimal rate of estimation errors for smooth functions, and thus, it is not straightforward to identify the theoretical advantages of DNNs. This study tries to _ll this gap by considering the estimation for a class of non-smooth functions that have singularities on hypersurfaces. Our findings are as follows: (i) We derive the generalization error of a DNN estimator and prove that its convergence rate is almost optimal. (ii) We elucidate a phase diagram of estimation problems, which describes the situations where the DNNs outperform a general class of estimators, including kernel methods, Gaussian process methods, and others. We additionally show that DNNs outperform harmonic analysis based estimators. This advantage of DNNs comes from the fact that a shape of singularity can be successfully handled by their multi-layered structure. | J79: Não | K79: RQ3; RQ5 | L79: Sem evidência suficiente para confirmar aderência temática ao escopo MAS–LLM no título/resumo. Registro também identificado em outra base ou categoria de busca.

Sheet Web of Science - Secundários
A1: Web of Science - Secundários
A2: Metadados organizados para rastreabilidade, auditoria e reprodução da RSL. Quantidade validada: 19 registros.
A4: ID do estudo | B4: Título | C4: Autores | D4: Ano | E4: Base de dados | F4: Tipo de estudo | G4: DOI | H4: Link | I4: Resumo | J4: Relevância para a pesquisa (Sim/Não) | K4: Questões de pesquisa atendidas (RQ1, RQ2, etc.) | L4: Observações
A5: S-WOS-001 | B5: AutoReview: An LLM-based Multi-Agent System for Security Issue-Oriented Code Review | C5: Chen, Yujia | D5: 2025 | E5: Web of Science | F5: Secundário | G5: 10.1145/3696630.3728618 | H5: https://doi.org/10.1145/3696630.3728618 | I5: Software vulnerabilities can lead to severe security issues such as data breaches, financial losses, and service disruptions, making security issue-oriented code review a crucial part of the development process. Traditional approaches struggle with analyzing complex code and providing explanations, while large language models (LLMs) show promise in code review but do not focus on security-related issues. To address these limitations, we propose AutoReview, an LLM-based multi-agent system for security code review. It integrates three agents: (1) Issue Detector identifying potential vulnerabilities using knowledge-level retrieval-augmented generation, (2) Issue Locator pinpoints the vulnerability positions through graph-based code slicing, and (3) Issue Repairer generating context-aware fixes via iterative verification. Evaluated on ReposVul with three code LLMs, AutoReview greatly demonstrates its effectiveness in security code reviews, improving F1-score for detection by 18.72\%, precision for location by 27.75\%, and BLEU for repair by 14.82\% over baselines. | J5: Sim | K5: RQ5 | L5: Confirma aderência temática ao escopo MAS–LLM no título/resumo. Registro sem duplicidade aparente no conjunto consolidado.
A6: S-WOS-002 | B6: A Survey on Trustworthy LLM Agents: Threats and Countermeasures | C6: Yu, Miao; Meng, Fanci; Zhou, Xinyun; Wang, Shilong; Mao, Junyuan; Pan, Linsey; Chen, Tianlong; Wang, Kun; Li, Xinfeng; Zhang, Yongfeng; An, Bo; Wen, Qingsong | D6: 2025 | E6: Web of Science | F6: Secundário | G6: 10.1145/3711896.3736561 | H6: https://doi.org/10.1145/3711896.3736561 | I6: With the rapid evolution of Large Language Models (LLMs), LLMbased agents and Multi-agent Systems (MAS) have significantly expanded the capabilities of LLM ecosystems. This evolution stems from empowering LLMs with additional modules such as memory, tools, environment, and even other agents. However, this advancement has also introduced more complex issues of trustworthiness, which previous research focusing solely on LLMs could not cover. In this survey, we propose the TrustAgent framework, a comprehensive study on the trustworthiness of agents, characterized by modular taxonomy, multi-dimensional connotations, and technical implementation. By thoroughly investigating and summarizing newly emerged attacks, defenses, and evaluation methods for agents and MAS, we extend the concept of Trustworthy LLM to the emerging paradigm of Trustworthy Agent. In TrustAgent, we begin by deconstructing and introducing various components of the Agent and MAS. Then, we categorize their trustworthiness into intrinsic (brain, memory, and tool) and extrinsic (user, agent, and environment) aspects. Subsequently, we delineate the multifaceted meanings of trustworthiness and elaborate on the implementation techniques of existing research related to these internal and external modules. Finally, we present our insights and outlook on this domain, aiming to provide guidance for future endeavors. For easy reference, we categorize all the studies mentioned in this survey according to our taxonomy, available at: https://github.com/Ymm-cll/TrustAgent. | J6: Sim | K6: RQ4; RQ6 | L6: Confirma aderência temática ao escopo MAS–LLM no título/resumo. Registro sem duplicidade aparente no conjunto consolidado.
A7: S-WOS-003 | B7: Comparing a Human's and a Multi-Agent System's Thematic Analysis: Assessing Qualitative Coding Consistency | C7: Simon, Sebastian; Sankaranarayanan, Sreecharan; Tajik, Elham; Borchers, Conrad; Shahrokhian, Bahar; Balzan, Francesco; Strauss, Sebastian; Viswanathan, Sree Aurovindh; Atas, Amine Hatun; Carapina, Mia; Liang, Li; Celik, Berkan | D7: 2025 | E7: Web of Science | F7: Secundário | G7: 10.1007/978-3-031-98420-4\_5 | H7: https://doi.org/10.1007/978-3-031-98420-4\_5 | I7: Large Language Models (LLMs) have demonstrated fluency in text generation and reasoning tasks. Consequently, the field has probed the ability of LLMs to automate qualitative analysis, including inductive thematic analysis (iTA), previously achieved through human reasoning only. Studies using LLMs for iTA have yielded mixed results so far. LLMs have successfully been used for isolated steps of iTA in hybrid setups. With recent advances in multi-agent systems (MAS) enabling complex reasoning and task execution through multiple, collaborating LLM agents, the first results point towards the possibility of automating sequences of the iTA process. However, previous work especially lacks methodological standards for assessing the reliability and validity of LLM-derived iTA. Thus, in this paper, we propose a method for assessing the quality of iTA systems based on consistency with human coding on a benchmark dataset. We present criteria for benchmark datasets and an expert blind review with this method on two iTA outputs: one iTA conducted by domain experts, and another fully automated with a MAS built on the Claude 3.5 Sonnet LLM. Results indicate a high level of consistency and contribute evidence that complex qualitative analysis methods common in AIED research can be carried out by MAS. | J7: Sim | K7: RQ5 | L7: Confirma aderência temática ao escopo MAS–LLM no título/resumo. Registro também identificado em outra base ou categoria de busca.
A8: S-WOS-004 | B8: Generation of Scientific Literature Surveys Based on Large Language Models (LLM) and Multi-Agent Systems (MAS) | C8: Qi, Ruihua; Li, Weilong; Lyu, Haobo | D8: 2025 | E8: Web of Science | F8: Secundário | G8: 10.1007/978-981-97-9443-0\_14 | H8: https://doi.org/10.1007/978-981-97-9443-0\_14 | I8: With the rapid increase in the number and speed of scientific publications, researchers face significant time pressure when conducting literature reviews. This paper presents an automatic literature review generation method leveraging large language models (LLMs) and multi-agent systems (MAS). By designing multiple agent roles, including reference parsing, analysis, generation, and integration agents-this method fully utilizes the natural language processing capabilities of LLMs and the collaborative strengths of MAS to produce high-quality literature reviews. In the NLPCC2024 evaluation task, our method excelled in multiple automatic evaluation metrics (such as SoftHeadingRecall and ROUGE) and manual evaluations, showcasing its great potential for practical applications. | J8: Sim | K8: RQ1 | L8: Confirma aderência temática ao escopo MAS–LLM no título/resumo. Registro sem duplicidade aparente no conjunto consolidado.
A9: S-WOS-005 | B9: Retrieval Augmented Multi-agent Recommender | C9: Ao, Xiao; Han, Shuxi; Li, Yeming; Ma, Heli; Zhang, Pengfei; Zou, Jie | D9: 2025 | E9: Web of Science | F9: Secundário | G9: 10.1145/3701716.3719231 | H9: https://doi.org/10.1145/3701716.3719231 | I9: Online review platforms are vital for shaping consumer choices and experiences in today's digital world. The AgentSociety Challenge focuses on advancing personalized recommendations with large language model (LLM) agents, aiming to enhance web interactions and user satisfaction. This paper presents the first-place solution for the AgentSociety Challenge Recommendation Track, by the team of the University of Electronic Science and Technology of China. We propose a recommendation framework based on large language models, integrating retrieval-augmented feature extraction and a data-driven multi-agent strategy. The core advantages of our approach lie in two key aspects. First, to optimize the representation of both products and users, we design a retrieval-augmented feature extraction mechanism that combines structured product attributes with unstructured user reviews, capturing both the objective characteristics of products and users' subjective preferences. Second, we introduce a data-driven multi-agent system that adaptively adjusts processing strategies based on the heterogeneous characteristics of different datasets, thereby effectively uncovering valuable latent information. Our method is built upon the Qwen-72B-Instruct model, with further optimizations in recommendation accuracy and system stability. Experimental results on three widely used datasets-Amazon, Goodreads, and Yelp-demonstrate significant improvements in recommendation performance. Ultimately, our solution achieved an overall hit rate score of 0.4744, representing a 101\% improvement over the baseline, showcasing its outstanding effectiveness in personalized recommendation tasks. | J9: Sim | K9: RQ4; RQ5 | L9: Confirma aderência temática ao escopo MAS–LLM no título/resumo. Registro sem duplicidade aparente no conjunto consolidado.
A10: S-WOS-006 | B10: LLM-Based Multi-Agent Decision-Making: Challenges and Future Directions | C10: Sun, Chuanneng; Huang, Songjun; Pompili, Dario | D10: 2025 | E10: Web of Science | F10: Secundário | G10: 10.1109/LRA.2025.3562371 | H10: https://doi.org/10.1109/LRA.2025.3562371 | I10: In recent years, Large Language Models (LLMs) have shown great abilities in various tasks, including question answering, arithmetic problem solving, and poetry writing, among others. Although research on LLM-as-an-agent has shown that LLM can be applied to Decision-Making (DM) and achieve decent results, the extension of LLM-based agents to Multi-Agent DM (MADM) is not trivial, as many aspects, such as coordination and communication between agents, are not considered in the DM frameworks of a single agent. To inspire more research on LLM-based MADM, in this letter, we survey the existing LLM-based single-agent and multi-agent decision-making frameworks and provide potential research directions for future research. In particular, we focus on the cooperative tasks of multiple agents with a common goal and communication among them. We also consider human-in/on-the-loop scenarios enabled by the language component in the framework. | J10: Sim | K10: RQ2; RQ4; RQ5; RQ6 | L10: Confirma aderência temática ao escopo MAS–LLM no título/resumo. Registro também identificado em outra base ou categoria de busca.
A11: S-WOS-007 | B11: An LLM-based multi-agent system to assist early-stage product design and evaluation | C11: Chen, Pei; Cai, Yichen; Zhou, Zihong; Yao, Jiayi; Li, Jiayang; You, Weitao; Sun, Lingyun | D11: 2026 | E11: Web of Science | F11: Secundário | G11: 10.1080/09544828.2026.2616583 | H11: https://doi.org/10.1080/09544828.2026.2616583 | I11: Conceptual design decisions critically influence product performance, cost, and sustainability, yet integrating rigorous feasibility evaluation early in this creative phase remains challenging. While generative AI accelerates concept generation, current methods often lack mechanisms to assess the feasibility of proposed designs. To bridge this gap, this paper presents DesignAgent, an LLM-based multi-agent system that assists early-stage product design and evaluation. The system features specialised agents that collaborate to interpret requirements, produce 3D prototypes, and automatically evaluate feasibility through integrated finite element analysis. This agent-driven framework facilitates an automated, iterative design loop where simulation feedback informs concept refinement. We evaluated the system through a case study involving 104 simulated design sessions for three types of UAV landing gear. A comprehensive assessment involving human expert review, AI (LLM) evaluation, and quantitative analysis demonstrates the high proficiency of the system. The system achieved over 90\% accuracy in core tasks, effectively utilised FEA feedback with an 84.3\% meaningful refinement rate, and also showed excellent adherence to engineering constraints and effective parameter refinement towards improved design quality. A user study further showed that DesignAgent achieved higher design accuracy and solution quality, lower workload, and better human-AI collaboration than the baseline systems. | J11: Sim | K11: RQ1; RQ4 | L11: Confirma aderência temática ao escopo MAS–LLM no título/resumo. Registro sem duplicidade aparente no conjunto consolidado.
A12: S-WOS-008 | B12: LABMATE: Language Model Based Multi-Agent System to Accelerate Catalysis Experiments | C12: Acharya, Anurag; Sharma, Anshu Kiran; Parker, Derek; Vega, Timothy; Ashraf, Rizwan A.; Isenberg, Natalie M.; Strube, Jan; Rallo, Robert | D12: 2025 | E12: Web of Science | F12: Secundário | G12: 10.1145/3731599.3767399 | H12: https://doi.org/10.1145/3731599.3767399 | I12: As Large Language Models (LLMs) have become increasingly commonplace, they have been shown to be useful to domains far beyond just linguistic tasks. However, they are still unreliable to make decisions due to their potential to hallucinate, and unable to perform complex tasks like running simulations that are essential to a field like Material Science. To solve this, we introduce LABMATE (LAnguage model Based Multi-agent system to Accelerate caTalysis Experiments), a human-in-the-loop copilot framework that utilizes LLM agents to make catalysis research faster. LABMATE allows the human experts to submit simulation runs, track particle sizes, run data analysis, perform literature review, and generate potential hypothesis all in one framework, thereby expediting the research process. When evaluated on the Chemistry and Material Science segments of major benchmarks, LABMATE performs comparable to or better than most frontier LLMs, showing that in addition to accelerating the experimental process, our framework is also on par in domain knowledge compared to using a simple LLM. These results show that the system is able to significantly aid and improve the research process for human scientists. Furthermore, since the core architecture of the system is domain-agnostic, it can easily be adapted to other domains. | J12: Sim | K12: RQ4 | L12: Confirma aderência temática ao escopo MAS–LLM no título/resumo. Registro sem duplicidade aparente no conjunto consolidado.
A13: S-WOS-009 | B13: ChatCAD: An MLLM-Guided Framework for Zero-shot CAD Drawing Restoration | C13: Tang, Jing; Xiao, Hongru; Li, Xiang; Wang, Wei; Gong, Zeyu | D13: 2025 | E13: Web of Science | F13: Secundário | G13: 10.1109/ICASSP49660.2025.10890248 | H13: https://doi.org/10.1109/ICASSP49660.2025.10890248 | I13: CAD drawing restoration is one of the most urgent needs in industrial manufacturing. The existing research focuses on the digitization of CAD drawings, However, there are actually many problems in digitized CAD drawings due to the upgrading of engineering drafting software, and it is difficult to repair reliably. In this paper, we use multi-modal large language models (MLLMs) to carry out digital CAD drawing restoration, and we use Retrieval-Augmented Generation (RAG) technology to inject engineering domain knowledge into MLLMs. In addition, a complete set of multiagent systems is constructed to realize restoration in accordance with the CAD drawing review process in the mechanical field. We collected 1,639 CAD drawings of bearing seats to evaluate our multi-agent system, verifying its reliability and robustness to various problematic drawings. Notably, ChatCAD also has a much simpler implementation than alternative methods trained on a huge dataset. | J13: Sim | K13: RQ4; RQ5 | L13: Confirma aderência temática ao escopo MAS–LLM no título/resumo. Registro também identificado em outra base ou categoria de busca.
A14: S-WOS-010 | B14: Application of Artificial Intelligence Generated Content in Medical Examinations | C14: Li, Rui; Wu, Tong | D14: 2025 | E14: Web of Science | F14: Secundário | G14: 10.2147/AMEP.S492895 | H14: https://doi.org/10.2147/AMEP.S492895 | I14: As the rapid development of large language model, artificial intelligence generated content (AIGC) presents novel opportunities for constructing medical examination questions. However, it is unclear about the way of effectively utilizing AIGC for designing medical questions. AIGC is characterized by its rapid response capabilities and high efficiency, as well as good performance in mimicking clinical realities. In this study, we revealed the limitations inherent in paper-based examinations, and provided a streamlined instruction for generating questions using AIGC, with a particular focus on multiple-choice questions, case study questions, and video questions. Manual review remains necessary to ensure the accuracy and quality of the generated content. Future development will be benefited from technologies like retrieval augmented generation, multi-agent system, and video generation technology. As AIGC continues to evolve, it is anticipated to bring transformative changes to medical examinations, enhancing the quality of examination preparation, and contributing to the effective cultivation of medical students. | J14: Sim | K14: RQ5 | L14: Confirma aderência temática ao escopo MAS–LLM no título/resumo. Registro sem duplicidade aparente no conjunto consolidado.
A15: S-WOS-011 | B15: Redefining Transportation Simulation: Multi-agent Models Powered by LLMs | C15: Calderon, Christian; Marti, Pasqual; Jordan, Jaume; Palanca, Javier; Julian, Vicente | D15: 2025 | E15: Web of Science | F15: Secundário | G15: 10.1007/978-3-032-05925-3\_6 | H15: https://doi.org/10.1007/978-3-032-05925-3\_6 | I15: Urban mobility systems are increasingly strained by dynamic societal demands, environmental pressures, and infrastructural limitations. Traditional simulation approachesrooted in fixed rules and simplified behavioural assumptionsstruggle to capture the complexity and variability of human travel decisions. This paper presents a novel framework that integrates Large Language Models (LLMs) into multi-agent mobility simulations to enable context-aware, adaptive, and intelligent decision-making in urban transport planning. Our approach leverages real-world survey data to generate diverse traveller profiles, embedding demographic, behavioural, and contextual factors into SimFleet, a cutting-edge mobility simulation platform. Unlike traditional rule-based models, our framework allows agents to learn, adapt, and refine their travel choices through iterative interactions with simulated urban environments. The framework, built on the SimFleet platform, is evaluated using diverse user profiles and varying levels of contextual information. Results show that LLM-driven agents can achieve high decision quality, behavioural consistency, and realistic adaptation over time. This work highlights the potential of combining LLM reasoning with multi-agent systems to support more intelligent, interpretable, and flexible simulation tools for urban mobility. | J15: Sim | K15: RQ4; RQ5 | L15: Confirma aderência temática ao escopo MAS–LLM no título/resumo. Registro sem duplicidade aparente no conjunto consolidado.
A16: S-WOS-012 | B16: Transforming Software Development: A Study on the Integration of Multi-Agent Systems and Large Language Models for Automatic Code Generation | C16: Ramirez-Rueda, Rolando; Benitez-Guerrero, Edgard; Mezura-Godoy, Carmen; Barcenas, Everardo | D16: 2024 | E16: Web of Science | F16: Secundário | G16: 10.1109/CONISOFT63288.2024.00013 | H16: https://doi.org/10.1109/CONISOFT63288.2024.00013 | I16: This paper explores the integration of Multi-Agent Systems (MAS) and Large Language Models (LLMs) for automatic code generation, addressing the limitations of traditional manual coding. By conducting a comprehensive review of existing literature and analyzing a practical case study, we demonstrate how MAS and LLMs can collaboratively enhance software development processes. The research focuses on the technical and theoretical challenges of this integration, highlighting the potential for improved productivity, adaptability, and quality in code generation. The findings contribute to AI-based software engineering by revealing new research directions in collective intelligence and automated programming. | J16: Sim | K16: RQ1; RQ5 | L16: Confirma aderência temática ao escopo MAS–LLM no título/resumo. Registro também identificado em outra base ou categoria de busca.
... A23: S-WOS-019 | B23: Identification of Microsatellite (SSR) and RAPD Markers Linked to Rice Blast Disease Resistance gene in Rice (Oryza sativa L.) | C23: Selvaraj, Immanuel C.; Nagarajan, Pothiraj; Thiyagarajan, K.; Bharathi, M.; Rabindran, R. | D23: 2011 | E23: Web of Science | F23: Secundário | G23: Não informado | H23: Não informado | I23: A mapping population comprising 220 F-2 individuals was developed by raising the selfed F-1 seed of a single hybrid plant, White Ponni x Moroberekan. Two hundred and twenty two F-3 families were phenotyped for blast resistance under artificial condition. Fifty random amplified polymorphic (RAPD) primers were used to identify parental polymorphism. Twelve RAPD markers which showed clear polymorphism were scored in the F-2 mapping population. Out of 12 markers, 11 loci (91.97 \%) fitted into the expected segregation ratio of 3:1 based on chi(2) - test at 0.05\% probability value. Four hundred microsatellite primer pairs were used in the parental survey, Out of which 52 simple sequence repeats (SSR) primers were polymorphic. Out of 52 marker loci, 44 marker loci (84.61\%) fitted into the expected Mendelian segregation ratio of 1:2:1 based on chi(2) - test at 0.05\% probability value. The multipoint analysis resulted in the construction of preliminary genetic linkage map with 40 loci. One way analysis of variance (ANOVA) was performed to identify the marker phenotype association which resulted in the identification of 23 SSR markers putatively associated for the six traits studied. Three SSR markers (RM 5757, RM 451 and RM 492 from chromosomes four and two) were linked for leaf blast resistance, six markers for days to flowering, nine markers for pigmentation trait, two markers for plant height, four markers for panicle length and seven markers linked for grain yield per plant. Out of 12 RAPD markers studied, 7 were found to be linked to three traits viz., leaf blast resistance (OPBB 5(258), OPBB 5(194), OPAL 16(940) and OPBD 12(680)), five markers for glume purple tip (GPT) and one marker for grain yield per plant based on single marker analysis. | J23: Não | K23: Não identificado | L23: Sem evidência suficiente para confirmar aderência temática ao escopo MAS–LLM no título/resumo. Registro sem duplicidade aparente no conjunto consolidado.

Sheet Base_Unificada_Apoio
A1: Base Unificada de Apoio
A2: Aba auxiliar para cálculos de consolidação, estatísticas e controle de deduplicação.
A4: ID | B4: Base | C4: Tipo | D4: Ano | E4: DOI | F4: Título | G4: Chave_Deduplicacao | H4: Registro_Unico | I4: Relevância | J4: Folha | K4: RQs
A5: P-IEEE-001 | B5: IEEE Xplore | C5: Primário | D5: 2023 | E5: 10.1109/ACSOS-C58168.2023.00048 | F5: Self-Adaptive Large Language Model (LLM)-Based Multiagent Systems | G5: doi::10.1109/acsos-c58168.2023.00048 | H5: 1 | I5: Sim | J5: IEEE - Estudos Primários | K5: RQ2; RQ4; RQ5
A6: P-IEEE-002 | B6: IEEE Xplore | C6: Primário | D6: 2025 | E6: 10.1109/ISPA67752.2025.00198 | F6: Decentralized Multi-Agent System with Trust-Aware Communication | G6: doi::10.1109/ispa67752.2025.00198 | H6: 1 | I6: Sim | J6: IEEE - Estudos Primários | K6: RQ2; RQ4; RQ5
A7: P-IEEE-003 | B7: IEEE Xplore | C7: Primário | D7: 2025 | E7: 10.1109/HPCC67675.2025.00184 | F7: Architecture Design of Multi-Agent LLM Systems in Railway Data Governance | G7: doi::10.1109/hpcc67675.2025.00184 | H7: 1 | I7: Sim | J7: IEEE - Estudos Primários | K7: RQ4; RQ5
A8: P-IEEE-004 | B8: IEEE Xplore | C8: Primário | D8: 2025 | E8: 10.1109/ICCWorkshops67674.2025.11162489 | F8: Network Function Orchestration with LLM based Multi-Agent System | G8: doi::10.1109/iccworkshops67674.2025.11162489 | H8: 1 | I8: Sim | J8: IEEE - Estudos Primários | K8: RQ4; RQ5
A9: P-IEEE-005 | B9: IEEE Xplore | C9: Primário | D9: 2003 | E9: 10.1109/ICMLC.2003.1264511 | F9: UML-based domain ontology modeling for multi-agent system | G9: doi::10.1109/icmlc.2003.1264511 | H9: 1 | I9: Não | J9: IEEE - Estudos Primários | K9: RQ3
A10: P-IEEE-006 | B10: IEEE Xplore | C10: Primário | D10: 2025 | E10: 10.1109/AICCSA66935.2025.11315267 | F10: MultiFuzz: A Dense Retrieval-based Multi-Agent System for Network Protocol Fuzzing | G10: doi::10.1109/aiccsa66935.2025.11315267 | H10: 1 | I10: Sim | J10: IEEE - Estudos Primários | K10: RQ1; RQ2; RQ4; RQ5; RQ6
A11: P-IEEE-007 | B11: IEEE Xplore | C11: Primário | D11: 2025 | E11: 10.1109/ETFA65518.2025.11205539 | F11: Control Industrial Automation System with Large Language Model Agents | G11: doi::10.1109/etfa65518.2025.11205539 | H11: 1 | I11: Não | J11: IEEE - Estudos Primários | K11: RQ4
A12: P-IEEE-008 | B12: IEEE Xplore | C12: Primário | D12: 2025 | E12: 10.1109/TCCN.2025.3528892 | F12: AutoHMA-LLM: Efficient Task Coordination and Execution in Heterogeneous Multi-Agent Systems Using Hybrid Large Language Models | G12: doi::10.1109/tccn.2025.3528892 | H12: 1 | I12: Sim | J12: IEEE - Estudos Primários | K12: RQ2; RQ4; RQ5
A13: P-IEEE-009 | B13: IEEE Xplore | C13: Primário | D13: 2025 | E13: 10.1109/ICDCSW63273.2025.00083 | F13: Distributed Multi-Agent AI Systems: Scalability, Challenges, and Applications | G13: doi::10.1109/icdcsw63273.2025.00083 | H13: 1 | I13: Não | J13: IEEE - Estudos Primários | K13: RQ2; RQ4; RQ5; RQ6
A14: P-IEEE-010 | B14: IEEE Xplore | C14: Primário | D14: 2023 | E14: 10.1109/CIC58953.2023.00021 | F14: Enabling Synergistic Knowledge Sharing and Reasoning in Large Language Models with Collaborative Multi-Agents | G14: doi::10.1109/cic58953.2023.00021 | H14: 1 | I14: Sim | J14: IEEE - Estudos Primários | K14: RQ2; RQ4; RQ5
A15: P-IEEE-011 | B15: IEEE Xplore | C15: Primário | D15: 2016 | E15: 10.1109/SITIS.2016.67 | F15: Onto2MAS: An Ontology-Based Framework for Automatic Multi-Agent System Generation | G15: doi::10.1109/sitis.2016.67 | H15: 1 | I15: Não | J15: IEEE - Estudos Primários | K15: RQ2; RQ3; RQ4
A16: P-IEEE-012 | B16: IEEE Xplore | C16: Primário | D16: 2024 | E16: 10.1109/BigData62323.2024.10825608 | F16: Leveraging Multi-Agent Systems and Large Language Models for Diabetes Knowledge Graphs | G16: doi::10.1109/bigdata62323.2024.10825608 | H16: 1 | I16: Sim | J16: IEEE - Estudos Primários | K16: RQ1; RQ3; RQ4; RQ5
... A440: S-WOS-019 | B440: Web of Science | C440: Secundário | D440: 2011 | E440: Não informado | F440: Identification of Microsatellite (SSR) and RAPD Markers Linked to Rice Blast Disease Resistance gene in Rice (Oryza sativa L.) | G440: titulo::identification of microsatellite ssr and rapd markers linked to rice blast disease resistance gene in rice oryza sativa l | H440: 1 | I440: Não | J440: Web of Science - Secundários | K440: Não identificado

Sheet Consolidação Geral da RSL
A1: Consolidação Geral da RSL
A2: Síntese quantitativa do corpus por base, categoria de busca e etapas principais de seleção.
A4: Base | B4: Estudos Primários | C4: Estudos Secundários | D4: Total
A5: IEEE Xplore | B5: =COUNTIFS(Base_Unificada_Apoio!$B$5:$B$440,$A5,Base_Unificada_Apoio!$C$5:$C$440,"Primário") -> 120 | C5: =COUNTIFS(Base_Unificada_Apoio!$B$5:$B$440,$A5,Base_Unificada_Apoio!$C$5:$C$440,"Secundário") -> 17 | D5: =SUM(B5:C5) -> 137
A6: ACM Digital Library | B6: =COUNTIFS(Base_Unificada_Apoio!$B$5:$B$440,$A6,Base_Unificada_Apoio!$C$5:$C$440,"Primário") -> 120 | C6: =COUNTIFS(Base_Unificada_Apoio!$B$5:$B$440,$A6,Base_Unificada_Apoio!$C$5:$C$440,"Secundário") -> 75 | D6: =SUM(B6:C6) -> 195
A7: Web of Science | B7: =COUNTIFS(Base_Unificada_Apoio!$B$5:$B$440,$A7,Base_Unificada_Apoio!$C$5:$C$440,"Primário") -> 85 | C7: =COUNTIFS(Base_Unificada_Apoio!$B$5:$B$440,$A7,Base_Unificada_Apoio!$C$5:$C$440,"Secundário") -> 19 | D7: =SUM(B7:C7) -> 104
A8: Total geral | B8: =SUM(B5:B7) -> 325 | C8: =SUM(C5:C7) -> 111 | D8: =SUM(D5:D7) -> 436
A10: Indicadores gerais da revisão
A11: Indicador | B11: Valor | C11: Observação
A12: Total geral de estudos identificados | B12: =COUNTA(Base_Unificada_Apoio!$A$5:$A$440) -> 436 | C12: Total de registros presentes nas seis abas de metadados.
A13: Total após remoção de duplicatas | B13: =SUM(Base_Unificada_Apoio!$H$5:$H$440) -> 325 | C13: Contagem de chaves únicas considerando DOI e, na ausência deste, título normalizado.
A14: Total após critérios de inclusão/exclusão | B14: =COUNTIFS(Base_Unificada_Apoio!$H$5:$H$440,1,Base_Unificada_Apoio!$I$5:$I$440,"Sim") -> 166 | C14: Triagem realizada a partir do título e do resumo, em conformidade com o protocolo da planilha.
A15: Total final analisado | B15: =B14 -> 166 | C15: Corresponde ao conjunto elegível após a triagem temática sobre os metadados.

Sheet Estatísticas da Revisão
A1: Estatísticas da Revisão
A2: Tabelas consolidadas para apoiar a leitura quantitativa do corpus da revisão.
A4: Distribuição por base
A5: Base | B5: Primários | C5: Secundários
A6: IEEE Xplore | B6: =COUNTIFS(Base_Unificada_Apoio!$B$5:$B$440,$A6,Base_Unificada_Apoio!$C$5:$C$440,"Primário") -> 120 | C6: =COUNTIFS(Base_Unificada_Apoio!$B$5:$B$440,$A6,Base_Unificada_Apoio!$C$5:$C$440,"Secundário") -> 17
A7: ACM Digital Library | B7: =COUNTIFS(Base_Unificada_Apoio!$B$5:$B$440,$A7,Base_Unificada_Apoio!$C$5:$C$440,"Primário") -> 120 | C7: =COUNTIFS(Base_Unificada_Apoio!$B$5:$B$440,$A7,Base_Unificada_Apoio!$C$5:$C$440,"Secundário") -> 75
A8: Web of Science | B8: =COUNTIFS(Base_Unificada_Apoio!$B$5:$B$440,$A8,Base_Unificada_Apoio!$C$5:$C$440,"Primário") -> 85 | C8: =COUNTIFS(Base_Unificada_Apoio!$B$5:$B$440,$A8,Base_Unificada_Apoio!$C$5:$C$440,"Secundário") -> 19
A11: Distribuição por tipo de estudo
A12: Tipo | B12: Quantidade
A13: Primário | B13: =B6+B7+B8 -> 325 | D13: Distribuição por ano
A14: Secundário | B14: =C6+C7+C8 -> 111 | D14: Ano | E14: Quantidade
D15: 1993 | E15: =COUNTIFS(Base_Unificada_Apoio!$D$5:$D$440,D15,Base_Unificada_Apoio!$H$5:$H$440,1) -> 2
D16: 2002 | E16: =COUNTIFS(Base_Unificada_Apoio!$D$5:$D$440,D16,Base_Unificada_Apoio!$H$5:$H$440,1) -> 2
D17: 2003 | E17: =COUNTIFS(Base_Unificada_Apoio!$D$5:$D$440,D17,Base_Unificada_Apoio!$H$5:$H$440,1) -> 1
D18: 2006 | E18: =COUNTIFS(Base_Unificada_Apoio!$D$5:$D$440,D18,Base_Unificada_Apoio!$H$5:$H$440,1) -> 1
D19: 2007 | E19: =COUNTIFS(Base_Unificada_Apoio!$D$5:$D$440,D19,Base_Unificada_Apoio!$H$5:$H$440,1) -> 2
D20: 2008 | E20: =COUNTIFS(Base_Unificada_Apoio!$D$5:$D$440,D20,Base_Unificada_Apoio!$H$5:$H$440,1) -> 3
D21: 2010 | E21: =COUNTIFS(Base_Unificada_Apoio!$D$5:$D$440,D21,Base_Unificada_Apoio!$H$5:$H$440,1) -> 4
D22: 2011 | E22: =COUNTIFS(Base_Unificada_Apoio!$D$5:$D$440,D22,Base_Unificada_Apoio!$H$5:$H$440,1) -> 3
D23: 2012 | E23: =COUNTIFS(Base_Unificada_Apoio!$D$5:$D$440,D23,Base_Unificada_Apoio!$H$5:$H$440,1) -> 1
D24: 2013 | E24: =COUNTIFS(Base_Unificada_Apoio!$D$5:$D$440,D24,Base_Unificada_Apoio!$H$5:$H$440,1) -> 4
D25: 2014 | E25: =COUNTIFS(Base_Unificada_Apoio!$D$5:$D$440,D25,Base_Unificada_Apoio!$H$5:$H$440,1) -> 5
D26: 2015 | E26: =COUNTIFS(Base_Unificada_Apoio!$D$5:$D$440,D26,Base_Unificada_Apoio!$H$5:$H$440,1) -> 3
... D37: 2026 | E37: =COUNTIFS(Base_Unificada_Apoio!$D$5:$D$440,D37,Base_Unificada_Apoio!$H$5:$H$440,1) -> 35

Sheet Rastreabilidade da Seleção
A1: Rastreabilidade da Seleção
A2: Registro sequencial das etapas principais da seleção e do refinamento do corpus.
A4: Etapa | B4: Quantidade de artigos | C4: Descrição
A5: Resultados iniciais da busca | B5: ='Consolidação Geral da RSL'!B12 -> 436 | C5: Total inicial recuperado nas buscas primárias e secundárias nas três bases.
A6: Após remoção de duplicatas | B6: ='Consolidação Geral da RSL'!B13 -> 325 | C6: Conjunto remanescente após consolidação por DOI e título normalizado.
A7: Triagem por título e resumo | B7: ='Consolidação Geral da RSL'!B13 -> 325 | C7: Os metadados deduplicados foram lidos para verificação de aderência temática ao foco MAS–LLM.
A8: Após critérios de inclusão/exclusão | B8: ='Consolidação Geral da RSL'!B14 -> 166 | C8: Registros considerados pertinentes ao escopo da revisão a partir dos critérios aplicados sobre título e resumo.
A9: Estudos incluídos na revisão | B9: ='Consolidação Geral da RSL'!B15 -> 166 | C9: Conjunto final analisado nesta planilha de apoio metodológico.

Sheet Controle de Deduplicação
A1: Controle de Deduplicação
A2: Controle das chaves utilizadas na consolidação, com indicação dos registros únicos e dos casos repetidos entre bases e categorias.
A4: Chave de deduplicação | B4: Quantidade de ocorrências | C4: Bases envolvidas | D4: Tipos envolvidos | E4: IDs relacionados | F4: Títulos relacionados | G4: DOI | H4: Status
A5: doi::10.1109/conisoft63288.2024.00013 | B5: 3 | C5: IEEE Xplore; Web of Science | D5: Primário; Secundário | E5: P-IEEE-041; S-IEEE-013; S-WOS-012 | F5: Transforming Software Development: A Study on the Integration of Multi-Agent Systems and Large Language Models for Automatic Code Generation | G5: 10.1109/CONISOFT63288.2024.00013 | H5: Duplicado
A6: doi::10.1109/lra.2025.3562371 | B6: 3 | C6: Web of Science; IEEE Xplore | D6: Primário; Secundário | E6: P-WOS-038; S-IEEE-012; S-WOS-006 | F6: LLM-Based Multi-Agent Decision-Making: Challenges and Future Directions | G6: 10.1109/LRA.2025.3562371 | H6: Duplicado
A7: doi::10.1109/tse.2025.3632508 | B7: 3 | C7: IEEE Xplore; Web of Science | D7: Primário; Secundário | E7: P-IEEE-071; P-WOS-060; S-IEEE-016 | F7: The Power of Small LLMs: A Multi-Agent for Code Generation via Dynamic Precaution Tuning | G7: 10.1109/TSE.2025.3632508 | H7: Duplicado
A8: doi::10.1007/978-3-031-98420-4\_5 | B8: 2 | C8: Web of Science | D8: Primário; Secundário | E8: P-WOS-056; S-WOS-003 | F8: Comparing a Human's and a Multi-Agent System's Thematic Analysis: Assessing Qualitative Coding Consistency | G8: 10.1007/978-3-031-98420-4\_5 | H8: Duplicado
A9: doi::10.1038/s41586-025-10097-9 | B9: 2 | C9: Web of Science | D9: Primário; Secundário | E9: P-WOS-065; S-WOS-017 | F9: An agentic system for rare disease diagnosis with traceable reasoning | G9: 10.1038/s41586-025-10097-9 | H9: Duplicado
A10: doi::10.1109/access.2025.3547172 | B10: 2 | C10: IEEE Xplore; Web of Science | D10: Primário | E10: P-IEEE-106; P-WOS-073 | F10: MAD-CTI: Cyber Threat Intelligence Analysis of the Dark Web Using a Multi-Agent Framework | G10: 10.1109/ACCESS.2025.3547172 | H10: Duplicado
A11: doi::10.1109/access.2025.3602681 | B11: 2 | C11: IEEE Xplore; Web of Science | D11: Primário | E11: P-IEEE-057; P-WOS-083 | F11: A Multi-Agent System for Cybersecurity Threat Detection and Correlation Using Large Language Models | G11: 10.1109/ACCESS.2025.3602681 | H11: Duplicado
A12: doi::10.1109/access.2025.3613340 | B12: 2 | C12: IEEE Xplore; Web of Science | D12: Primário | E12: P-IEEE-031; P-WOS-037 | F12: An Adaptive Multi-Agent LLM-Based Clinical Decision Support System Integrating Biomedical RAG and Web Intelligence | G12: 10.1109/ACCESS.2025.3613340 | H12: Duplicado
A13: doi::10.1109/cain66642.2025.00031 | B13: 2 | C13: IEEE Xplore; Web of Science | D13: Primário | E13: P-IEEE-062; P-WOS-028 | F13: Engineering LLM Powered Multi-Agent Framework for Autonomous CloudOps | G13: 10.1109/CAIN66642.2025.00031 | H13: Duplicado
A14: doi::10.1109/cain66642.2025.00039 | B14: 2 | C14: IEEE Xplore; Web of Science | D14: Primário | E14: P-IEEE-052; P-WOS-025 | F14: Assessing and Enhancing the Robustness of LLM-Based Multi-Agent Systems Through Chaos Engineering | Assessing and Enhancing the Robustness of LLM-based Multi-Agent Systems Through Chaos Engineering | G14: 10.1109/CAIN66642.2025.00039 | H14: Duplicado
A15: doi::10.1109/ccwc67433.2026.11393746 | B15: 2 | C15: IEEE Xplore | D15: Primário; Secundário | E15: P-IEEE-019; S-IEEE-005 | F15: Analysing the Role of Multi-Agent AI Models for Autonomous Business Decision Systems | G15: 10.1109/CCWC67433.2026.11393746 | H15: Duplicado
A16: doi::10.1109/cic58953.2023.00021 | B16: 2 | C16: IEEE Xplore; Web of Science | D16: Primário | E16: P-IEEE-010; P-WOS-017 | F16: Enabling Synergistic Knowledge Sharing and Reasoning in Large Language Models with Collaborative Multi-Agents | G16: 10.1109/CIC58953.2023.00021 | H16: Duplicado
... A329: titulo::unlocking the potential of decentralized llm based mas privacy preservation and monetization in collective intelligence | B329: 1 | C329: Web of Science | D329: Primário | E329: P-WOS-077 | F329: Unlocking the Potential of Decentralized LLM-based MAS: Privacy Preservation and Monetization in Collective Intelligence | G329: Não informado | H329: Único

Sheet Procedimento Metodológico
A1: Procedimento Metodológico
A2: Síntese do protocolo empregado para organização, conferência, deduplicação e triagem dos metadados da revisão.
A4: Etapa | B4: Descrição metodológica | C4: Registro na planilha
A5: 1. Coleta dos metadados | B5: Os metadados foram preservados por base e por categoria de busca (estudos primários e estudos secundários), mantendo a separação original para rastreabilidade. | C5: Seis abas de metadados: IEEE, ACM e Web of Science, em primários e secundários.
A6: 2. Conferência das quantidades | B6: As quantidades foram validadas com base nos arquivos exportados e na conferência manual dos resultados. | C6: Aba Consolidação geral com totais por base.
A7: 3. Normalização dos campos | B7: Foram padronizados os campos essenciais para leitura comparável: título, autores, ano, base, tipo de estudo, DOI, link e resumo. | C7: Estrutura uniforme nas seis abas principais.
A8: 4. Deduplicação auditável | B8: A consolidação utilizou como chave preferencial o DOI e, na ausência deste, o título normalizado. Cada chave foi registrada em aba própria. | C8: Aba "Controle de Deduplicação" e coluna auxiliar de consolidação.
A9: 5. Triagem temática | B9: A aderência ao tema foi verificada a partir do título e do resumo, considerando a presença simultânea de termos relacionados a MAS, LLM e às questões de pesquisa do estudo. A classificação no campo “Questões de pesquisa atendidas” foi realizada com base na leitura e análise dos estudos, seguindo os critérios definidos no protocolo da revisão para cada RQ. | C9: Colunas "Relevância para a pesquisa" e "Questões de pesquisa atendidas".
A10: 6. Consolidação final | B10: Os totais gerais, estatísticas e a rastreabilidade das etapas foram organizados em abas sintéticas para permitir auditoria metodológica do corpus. | C10: Abas "Consolidação Geral da RSL", "Estatísticas da Revisão" e "Rastreabilidade da Seleção".
A11: 7. Observação específica da IEEE | B11: Para o conjunto primário da IEEE, embora a exportação inicial tenha retornado um número superior de registros, foi identificada a presença de inconsistências nos metadados, incluindo duplicidades, registros incompletos e entradas não recuperadas corretamente durante o processo de exportação. Dessa forma, foi realizada uma conferência manual criteriosa, resultando em um total validado de 120 estudos primários efetivamente distintos e elegíveis. Esse procedimento foi adotado para garantir a qualidade, consistência e rastreabilidade dos dados utilizados na revisão, alinhando os resultados às condições reais de recuperação dos estudos na base. | C11: Aba "IEEE - Estudos Primários".

Sheet Legenda
A1: Legenda de apoio
A2: Descrição sucinta das colunas de triagem presentes nas abas principais.
A4: Campo | B4: Significado | C4: Observação
A5: Relevância para a pesquisa | B5: Indica se o metadado apresenta evidência suficiente de aderência ao foco MAS–LLM no título e no resumo. | C5: Usada para a etapa de triagem temática.
A6: Questões de pesquisa atendidas | B6: Registra, quando aplicável, a associação do estudo com as RQs do protocolo analítico. | C6: Os códigos podem aparecer combinados no mesmo registro.
A7: Observações | B7: Campo narrativo curto para registrar aderência temática e eventual duplicidade. | C7: Mantido em linguagem descritiva para facilitar a auditoria.
A8: Chave de deduplicação | B8: DOI do registro ou, quando ausente, título normalizado. | C8: Utilizada na consolidação geral e no controle de deduplicação.

Sheet Síntese Questões Pesquisa
A1: Síntese das Questões de Pesquisa
A2: Síntese estatística dos registros únicos e relevantes da aba Base_Unificada_Apoio.
A3: Corpus analisado: 166 artigos relevantes com Registro_Unico = 1.
A5: 1. Cobertura das Questões de Pesquisa | E5: 2. Distribuição das Questões por Base
A6: Questão de Pesquisa | B6: Artigos que respondem | C6: Percentual do corpus | E6: Base | F6: RQ1 | G6: RQ2 | H6: RQ3 | I6: RQ4 | J6: RQ5 | K6: RQ6
A7: RQ1 | B7: 38 | C7: 0.229 | E7: IEEE Xplore | F7: 19 | G7: 39 | H7: 8 | I7: 71 | J7: 67 | K7: 8
A8: RQ2 | B8: 75 | C8: 0.452 | E8: ACM Digital Library | F8: 3 | G8: 2 | H8: 0 | I8: 5 | J8: 9 | K8: 3
A9: RQ3 | B9: 21 | C9: 0.127 | E9: Web of Science | F9: 16 | G9: 34 | H9: 13 | I9: 47 | J9: 51 | K9: 3
A10: RQ4 | B10: 123 | C10: 0.741
A11: RQ5 | B11: 127 | C11: 0.765
A12: RQ6 | B12: 14 | C12: 0.084
A15: 3. Intensidade de Cobertura das RQs
A16: Número de RQs atendidas por artigo | B16: Quantidade de artigos
A17: 1 RQ | B17: 28
A18: 2 RQs | B18: 63
A19: 3 RQs | B19: 58
A20: 4 RQs | B20: 15
A21: 5 RQs | B21: 2
A22: 6 RQs | B22: 0
A23: Total | B23: 166 | C23: teste
C24: teste
A25: 4. Rastreamento dos Estudos por Questão | C25: teste
A26: ID do Estudo | B26: Base | C26: Tipo de Estudo | D26: Questões de Pesquisa Atendidas
A27: P-ACM-009 | B27: ACM Digital Library | C27: Primário | D27: RQ4; RQ5
A28: P-ACM-015 | B28: ACM Digital Library | C28: Primário | D28: RQ5; RQ6
A29: P-ACM-021 | B29: ACM Digital Library | C29: Primário | D29: RQ1; RQ5; RQ6
A30: P-ACM-022 | B30: ACM Digital Library | C30: Primário | D30: RQ1; RQ2; RQ4; RQ5
A31: P-ACM-024 | B31: ACM Digital Library | C31: Primário | D31: RQ2; RQ4; RQ5
A32: P-ACM-026 | B32: ACM Digital Library | C32: Primário | D32: RQ1; RQ4; RQ5
A33: P-ACM-031 | B33: ACM Digital Library | C33: Primário | D33: RQ4; RQ5
A34: P-ACM-032 | B34: ACM Digital Library | C34: Primário | D34: RQ5; RQ6
A35: P-ACM-043 | B35: ACM Digital Library | C35: Primário | D35: RQ5
A36: P-IEEE-001 | B36: IEEE Xplore | C36: Primário | D36: RQ2; RQ4; RQ5
A37: P-IEEE-002 | B37: IEEE Xplore | C37: Primário | D37: RQ2; RQ4; RQ5
... A192: S-WOS-018 | B192: Web of Science | C192: Secundário | D192: RQ5

Sheet Protocolo_Extracao
A1: RQ | B1: Dimensão investigada | C1: Categoria operacional | D1: Critério de inclusão | E1: Evidências consideradas | F1: Critério de consolidação | G1: Unidade de contagem | H1: Denominador do percentual | I1: Sobreposição | J1: Uso nos resultados | K1: Exemplos de estudos
A2: RQ1 | B2: Ferramentas, frameworks, plataformas e tecnologias de suporte | C2: Frameworks e plataformas gerais | D2: Evidência genérica de ferramenta, plataforma ou tecnologia MAS--LLM | E2: Ferramentas ou plataformas reutilizáveis para criação, coordenação ou execução de agentes LLM. | F2: Evidências semanticamente equivalentes ou funcionalmente próximas foram consolidadas nesta categoria. | G2: Estudo único que reporta ao menos uma evidência da categoria; não se conta o número de menções textuais. | H2: Total de estudos classificados na RQ1: 38 | I2: Categoria sobreposta: o mesmo estudo pode aparecer em mais de uma categoria da mesma RQ. | J2: Usada para calcular incidência, percentual, predominância e temas emergentes na resposta da RQ. | K2: P-IEEE-015; P-IEEE-022; P-IEEE-041; P-IEEE-043
A3: RQ1 | B3: Ferramentas, frameworks, plataformas e tecnologias de suporte | C3: Plataformas especializadas por domínio | D3: Solução MAS--LLM proposta ou aplicada em domínio específico | E3: Soluções MAS--LLM propostas para domínios específicos, como IoT, redes, manufatura ou blockchain. | F3: Evidências semanticamente equivalentes ou funcionalmente próximas foram consolidadas nesta categoria. | G3: Estudo único que reporta ao menos uma evidência da categoria; não se conta o número de menções textuais. | H3: Total de estudos classificados na RQ1: 38 | I3: Categoria sobreposta: o mesmo estudo pode aparecer em mais de uma categoria da mesma RQ. | J3: Usada para calcular incidência, percentual, predominância e temas emergentes na resposta da RQ. | K3: P-ACM-026; P-IEEE-006; P-IEEE-012; P-IEEE-055
A4: RQ1 | B4: Ferramentas, frameworks, plataformas e tecnologias de suporte | C4: RAG, bases de conhecimento e memória | D4: Integração com recuperação, bases de conhecimento, grafos ou memória contextual | E4: Uso de RAG, grafos de conhecimento, bases vetoriais, memória ou recuperação contextual. | F4: Evidências semanticamente equivalentes ou funcionalmente próximas foram consolidadas nesta categoria. | G4: Estudo único que reporta ao menos uma evidência da categoria; não se conta o número de menções textuais. | H4: Total de estudos classificados na RQ1: 38 | I4: Categoria sobreposta: o mesmo estudo pode aparecer em mais de uma categoria da mesma RQ. | J4: Usada para calcular incidência, percentual, predominância e temas emergentes na resposta da RQ. | K4: P-ACM-021; P-ACM-022; P-ACM-026; P-IEEE-006
A5: RQ1 | B5: Ferramentas, frameworks, plataformas e tecnologias de suporte | C5: Observabilidade, auditoria e governança | D5: Monitoramento, rastreabilidade, confiança, auditoria ou governança de agentes | E5: Monitoramento, rastreabilidade, auditoria, confiança, governança ou AgentOps. | F5: Evidências semanticamente equivalentes ou funcionalmente próximas foram consolidadas nesta categoria. | G5: Estudo único que reporta ao menos uma evidência da categoria; não se conta o número de menções textuais. | H5: Total de estudos classificados na RQ1: 38 | I5: Categoria sobreposta: o mesmo estudo pode aparecer em mais de uma categoria da mesma RQ. | J5: Usada para calcular incidência, percentual, predominância e temas emergentes na resposta da RQ. | K5: P-ACM-026; P-IEEE-110; S-WOS-007
A6: RQ1 | B6: Ferramentas, frameworks, plataformas e tecnologias de suporte | C6: Protocolos e interoperabilidade | D6: Uso ou proposta de protocolos, APIs ou mecanismos de acoplamento entre agentes, serviços e ferramentas | E6: Protocolos, APIs ou mecanismos de acoplamento entre agentes, ferramentas, dados e serviços. | F6: Evidências semanticamente equivalentes ou funcionalmente próximas foram consolidadas nesta categoria. | G6: Estudo único que reporta ao menos uma evidência da categoria; não se conta o número de menções textuais. | H6: Total de estudos classificados na RQ1: 38 | I6: Categoria sobreposta: o mesmo estudo pode aparecer em mais de uma categoria da mesma RQ. | J6: Usada para calcular incidência, percentual, predominância e temas emergentes na resposta da RQ. | K6: P-IEEE-006; P-IEEE-027
A7: RQ2 | B7: Mecanismos de orquestração, comunicação, interoperabilidade, contexto e governança | C7: Orquestração e coordenação de tarefas | D7: Evidência geral de coordenação MAS--LLM | E7: Distribuição de subtarefas, planejamento, controle de fluxo, coordenação ou gerenciamento de agentes. | F7: Evidências semanticamente equivalentes ou funcionalmente próximas foram consolidadas nesta categoria. | G7: Estudo único que reporta ao menos uma evidência da categoria; não se conta o número de menções textuais. | H7: Total de estudos classificados na RQ2: 75 | I7: Categoria sobreposta: o mesmo estudo pode aparecer em mais de uma categoria da mesma RQ. | J7: Usada para calcular incidência, percentual, predominância e temas emergentes na resposta da RQ. | K7: P-ACM-022; P-IEEE-001; P-IEEE-008; P-IEEE-013
A8: RQ2 | B8: Mecanismos de orquestração, comunicação, interoperabilidade, contexto e governança | C8: Comunicação e negociação entre agentes | D8: Troca de mensagens, consenso, negociação, colaboração ou compartilhamento de raciocínio | E8: Troca de mensagens, group chat, handoffs, negociação, consenso ou colaboração entre agentes. | F8: Evidências semanticamente equivalentes ou funcionalmente próximas foram consolidadas nesta categoria. | G8: Estudo único que reporta ao menos uma evidência da categoria; não se conta o número de menções textuais. | H8: Total de estudos classificados na RQ2: 75 | I8: Categoria sobreposta: o mesmo estudo pode aparecer em mais de uma categoria da mesma RQ. | J8: Usada para calcular incidência, percentual, predominância e temas emergentes na resposta da RQ. | K8: P-IEEE-002; P-IEEE-010; P-IEEE-027; P-IEEE-050
A9: RQ2 | B9: Mecanismos de orquestração, comunicação, interoperabilidade, contexto e governança | C9: Governança e humano-no-laço | D9: Participação humana, validação, controle, governança ou supervisão da execução | E9: Supervisão humana, validação, controle, auditoria ou governança da execução. | F9: Evidências semanticamente equivalentes ou funcionalmente próximas foram consolidadas nesta categoria. | G9: Estudo único que reporta ao menos uma evidência da categoria; não se conta o número de menções textuais. | H9: Total de estudos classificados na RQ2: 75 | I9: Categoria sobreposta: o mesmo estudo pode aparecer em mais de uma categoria da mesma RQ. | J9: Usada para calcular incidência, percentual, predominância e temas emergentes na resposta da RQ. | K9: P-IEEE-002; P-IEEE-026; P-IEEE-048; P-IEEE-055
A10: RQ2 | B10: Mecanismos de orquestração, comunicação, interoperabilidade, contexto e governança | C10: Contexto, memória e conhecimento compartilhado | D10: Uso de memória, contexto, RAG, grafos ou conhecimento compartilhado entre agentes | E10: Uso ou compartilhamento de contexto, memória, conhecimento, RAG ou grafos entre agentes. | F10: Evidências semanticamente equivalentes ou funcionalmente próximas foram consolidadas nesta categoria. | G10: Estudo único que reporta ao menos uma evidência da categoria; não se conta o número de menções textuais. | H10: Total de estudos classificados na RQ2: 75 | I10: Categoria sobreposta: o mesmo estudo pode aparecer em mais de uma categoria da mesma RQ. | J10: Usada para calcular incidência, percentual, predominância e temas emergentes na resposta da RQ. | K10: P-ACM-022; P-ACM-024; P-IEEE-006; P-IEEE-010
A11: RQ2 | B11: Mecanismos de orquestração, comunicação, interoperabilidade, contexto e governança | C11: Interoperabilidade com ferramentas e serviços | D11: Integração com APIs, serviços externos, dados, infraestrutura ou ferramentas de execução | E11: Integração com APIs, bancos de dados, serviços externos, nuvem, borda ou ferramentas de execução. | F11: Evidências semanticamente equivalentes ou funcionalmente próximas foram consolidadas nesta categoria. | G11: Estudo único que reporta ao menos uma evidência da categoria; não se conta o número de menções textuais. | H11: Total de estudos classificados na RQ2: 75 | I11: Categoria sobreposta: o mesmo estudo pode aparecer em mais de uma categoria da mesma RQ. | J11: Usada para calcular incidência, percentual, predominância e temas emergentes na resposta da RQ. | K11: P-IEEE-006; P-IEEE-050; P-IEEE-058; P-IEEE-074
A12: RQ3 | B12: Desafios, limitações, riscos e barreiras técnicas | C12: Coordenação, alinhamento e decisão | D12: Dificuldades de coordenação, alinhamento, decisão ou colaboração multiagente | E12: Dificuldades de coordenação, alinhamento de objetivos, tomada de decisão ou colaboração. | F12: Evidências semanticamente equivalentes ou funcionalmente próximas foram consolidadas nesta categoria. | G12: Estudo único que reporta ao menos uma evidência da categoria; não se conta o número de menções textuais. | H12: Total de estudos classificados na RQ3: 21 | I12: Categoria sobreposta: o mesmo estudo pode aparecer em mais de uma categoria da mesma RQ. | J12: Usada para calcular incidência, percentual, predominância e temas emergentes na resposta da RQ. | K12: P-IEEE-012; P-IEEE-028; P-IEEE-033; P-IEEE-054
... A32: RQ6 | B32: Lacunas de pesquisa e oportunidades futuras | C32: Segurança, governança e auditabilidade | D32: Necessidade de segurança, governança, auditoria, rastreabilidade ou controle de riscos | E32: Lacunas em segurança, governança, auditoria, rastreabilidade ou controle de riscos. | F32: Evidências semanticamente equivalentes ou funcionalmente próximas foram consolidadas nesta categoria. | G32: Estudo único que reporta ao menos uma evidência da categoria; não se conta o número de menções textuais. | H32: Total de estudos classificados na RQ6: 14 | I32: Categoria sobreposta: o mesmo estudo pode aparecer em mais de uma categoria da mesma RQ. | J32: Usada para calcular incidência, percentual, predominância e temas emergentes na resposta da RQ. | K32: P-IEEE-063

Sheet Matriz_Extracao_Evidencias
A1: ID_Estudo | B1: Título | C1: Base | D1: Tipo | E1: RQ | F1: Dimensão investigada | G1: Categoria operacional | H1: Evidência/indicador identificado | I1: Justificativa da classificação | J1: Unidade de contagem | K1: Regra de consolidação | L1: Denominador da RQ | M1: Uso na síntese
A2: P-ACM-009 | B2: Extended Reality Cybersickness Assessment via User Review Analysis | C2: ACM Digital Library | D2: Primário | E2: RQ4 | F2: Arquiteturas, estratégias de coordenação e gerenciamento de agentes | G2: Arquiteturas com supervisão humana ou governança | H2: Extended Reality Cybersickness Assessment via User Review Analysis | I2: Participação humana, suporte, auditoria, segurança ou governança na arquitetura | J2: Estudo único | K2: Uma linha representa a associação estudo--RQ--categoria; categorias podem ser sobrepostas. | L2: 123 | M2: Alimenta a contagem da aba Sintese_Incidencia_RQs por RQ e categoria.
A3: P-ACM-009 | B3: Extended Reality Cybersickness Assessment via User Review Analysis | C3: ACM Digital Library | D3: Primário | E3: RQ5 | F3: Domínios e tipos de aplicação prática | G3: Gestão de conhecimento e apoio à decisão | H3: Extended Reality Cybersickness Assessment via User Review Analysis | I3: Aplicações em recuperação de conhecimento, governança de dados, análise ou decisão | J3: Estudo único | K3: Uma linha representa a associação estudo--RQ--categoria; categorias podem ser sobrepostas. | L3: 127 | M3: Alimenta a contagem da aba Sintese_Incidencia_RQs por RQ e categoria.
A4: P-ACM-015 | B4: LLM-Based Multi-Agent Systems for Software Engineering: Literature Review, Vision, and the Road Ahead | C4: ACM Digital Library | D4: Primário | E4: RQ5 | F4: Domínios e tipos de aplicação prática | G4: Engenharia de software e processos de negócio | H4: LLM-Based Multi-Agent Systems for Software Engineering: Literature Review, Vision, and the Road Ahead | I4: Aplicações em desenvolvimento, testes, requisitos, DevOps, processos empresariais ou recomendação | J4: Estudo único | K4: Uma linha representa a associação estudo--RQ--categoria; categorias podem ser sobrepostas. | L4: 127 | M4: Alimenta a contagem da aba Sintese_Incidencia_RQs por RQ e categoria.
A5: P-ACM-015 | B5: LLM-Based Multi-Agent Systems for Software Engineering: Literature Review, Vision, and the Road Ahead | C5: ACM Digital Library | D5: Primário | E5: RQ6 | F5: Lacunas de pesquisa e oportunidades futuras | G5: Avaliação, métricas e reprodutibilidade | H5: LLM-Based Multi-Agent Systems for Software Engineering: Literature Review, Vision, and the Road Ahead | I5: Necessidade de benchmarks, métricas, comparação, validação ou reprodutibilidade | J5: Estudo único | K5: Uma linha representa a associação estudo--RQ--categoria; categorias podem ser sobrepostas. | L5: 14 | M5: Alimenta a contagem da aba Sintese_Incidencia_RQs por RQ e categoria.
A6: P-ACM-021 | B6: Automated Soap Opera Testing Directed by LLMs and Scenario Knowledge: Feasibility, Challenges, and Road Ahead | C6: ACM Digital Library | D6: Primário | E6: RQ1 | F6: Ferramentas, frameworks, plataformas e tecnologias de suporte | G6: RAG, bases de conhecimento e memória | H6: Automated Soap Opera Testing Directed by LLMs and Scenario Knowledge: Feasibility, Challenges, and Road Ahead | I6: Integração com recuperação, bases de conhecimento, grafos ou memória contextual | J6: Estudo único | K6: Uma linha representa a associação estudo--RQ--categoria; categorias podem ser sobrepostas. | L6: 38 | M6: Alimenta a contagem da aba Sintese_Incidencia_RQs por RQ e categoria.
A7: P-ACM-021 | B7: Automated Soap Opera Testing Directed by LLMs and Scenario Knowledge: Feasibility, Challenges, and Road Ahead | C7: ACM Digital Library | D7: Primário | E7: RQ5 | F7: Domínios e tipos de aplicação prática | G7: Engenharia de software e processos de negócio | H7: Automated Soap Opera Testing Directed by LLMs and Scenario Knowledge: Feasibility, Challenges, and Road Ahead | I7: Aplicações em desenvolvimento, testes, requisitos, DevOps, processos empresariais ou recomendação | J7: Estudo único | K7: Uma linha representa a associação estudo--RQ--categoria; categorias podem ser sobrepostas. | L7: 127 | M7: Alimenta a contagem da aba Sintese_Incidencia_RQs por RQ e categoria.
A8: P-ACM-021 | B8: Automated Soap Opera Testing Directed by LLMs and Scenario Knowledge: Feasibility, Challenges, and Road Ahead | C8: ACM Digital Library | D8: Primário | E8: RQ5 | F8: Domínios e tipos de aplicação prática | G8: Gestão de conhecimento e apoio à decisão | H8: Automated Soap Opera Testing Directed by LLMs and Scenario Knowledge: Feasibility, Challenges, and Road Ahead | I8: Aplicações em recuperação de conhecimento, governança de dados, análise ou decisão | J8: Estudo único | K8: Uma linha representa a associação estudo--RQ--categoria; categorias podem ser sobrepostas. | L8: 127 | M8: Alimenta a contagem da aba Sintese_Incidencia_RQs por RQ e categoria.
A9: P-ACM-021 | B9: Automated Soap Opera Testing Directed by LLMs and Scenario Knowledge: Feasibility, Challenges, and Road Ahead | C9: ACM Digital Library | D9: Primário | E9: RQ6 | F9: Lacunas de pesquisa e oportunidades futuras | G9: Avaliação, métricas e reprodutibilidade | H9: Automated Soap Opera Testing Directed by LLMs and Scenario Knowledge: Feasibility, Challenges, and Road Ahead | I9: Necessidade de benchmarks, métricas, comparação, validação ou reprodutibilidade | J9: Estudo único | K9: Uma linha representa a associação estudo--RQ--categoria; categorias podem ser sobrepostas. | L9: 14 | M9: Alimenta a contagem da aba Sintese_Incidencia_RQs por RQ e categoria.
A10: P-ACM-022 | B10: SagaLLM: Context Management, Validation, and Transaction Guarantees for Multi-Agent LLM Planning | C10: ACM Digital Library | D10: Primário | E10: RQ1 | F10: Ferramentas, frameworks, plataformas e tecnologias de suporte | G10: RAG, bases de conhecimento e memória | H10: SagaLLM: Context Management, Validation, and Transaction Guarantees for Multi-Agent LLM Planning | I10: Integração com recuperação, bases de conhecimento, grafos ou memória contextual | J10: Estudo único | K10: Uma linha representa a associação estudo--RQ--categoria; categorias podem ser sobrepostas. | L10: 38 | M10: Alimenta a contagem da aba Sintese_Incidencia_RQs por RQ e categoria.
A11: P-ACM-022 | B11: SagaLLM: Context Management, Validation, and Transaction Guarantees for Multi-Agent LLM Planning | C11: ACM Digital Library | D11: Primário | E11: RQ2 | F11: Mecanismos de orquestração, comunicação, interoperabilidade, contexto e governança | G11: Orquestração e coordenação de tarefas | H11: SagaLLM: Context Management, Validation, and Transaction Guarantees for Multi-Agent LLM Planning | I11: Distribuição de subtarefas, planejamento, controle de fluxo ou coordenação de agentes | J11: Estudo único | K11: Uma linha representa a associação estudo--RQ--categoria; categorias podem ser sobrepostas. | L11: 75 | M11: Alimenta a contagem da aba Sintese_Incidencia_RQs por RQ e categoria.
A12: P-ACM-022 | B12: SagaLLM: Context Management, Validation, and Transaction Guarantees for Multi-Agent LLM Planning | C12: ACM Digital Library | D12: Primário | E12: RQ2 | F12: Mecanismos de orquestração, comunicação, interoperabilidade, contexto e governança | G12: Contexto, memória e conhecimento compartilhado | H12: SagaLLM: Context Management, Validation, and Transaction Guarantees for Multi-Agent LLM Planning | I12: Uso de memória, contexto, RAG, grafos ou conhecimento compartilhado entre agentes | J12: Estudo único | K12: Uma linha representa a associação estudo--RQ--categoria; categorias podem ser sobrepostas. | L12: 75 | M12: Alimenta a contagem da aba Sintese_Incidencia_RQs por RQ e categoria.
A13: P-ACM-022 | B13: SagaLLM: Context Management, Validation, and Transaction Guarantees for Multi-Agent LLM Planning | C13: ACM Digital Library | D13: Primário | E13: RQ4 | F13: Arquiteturas, estratégias de coordenação e gerenciamento de agentes | G13: Arquiteturas híbridas, distribuídas ou colaborativas | H13: SagaLLM: Context Management, Validation, and Transaction Guarantees for Multi-Agent LLM Planning | I13: Organização com colaboração distribuída, autonomia, hibridismo ou coordenação descentralizada | J13: Estudo único | K13: Uma linha representa a associação estudo--RQ--categoria; categorias podem ser sobrepostas. | L13: 123 | M13: Alimenta a contagem da aba Sintese_Incidencia_RQs por RQ e categoria.
... A562: S-WOS-018 | B562: Towards language-based retrieval of complex geospatial data: A case study on UK National geographic database | C562: Web of Science | D562: Secundário | E562: RQ5 | F562: Domínios e tipos de aplicação prática | G562: Gestão de conhecimento e apoio à decisão | H562: Towards language-based retrieval of complex geospatial data: A case study on UK National geographic database | I562: Aplicações em recuperação de conhecimento, governança de dados, análise ou decisão | J562: Estudo único | K562: Uma linha representa a associação estudo--RQ--categoria; categorias podem ser sobrepostas. | L562: 127 | M562: Alimenta a contagem da aba Sintese_Incidencia_RQs por RQ e categoria.

Sheet Sintese_Incidencia_RQs
A1: RQ | B1: Dimensão investigada | C1: Total_RQ | D1: Categoria operacional | E1: Estudos_na_categoria | F1: Percentual_sobre_RQ | G1: Regra de cálculo | H1: Tipo de categoria | I1: Papel na síntese | J1: Interpretação para os resultados | K1: Observação metodológica
A2: RQ1 | B2: Ferramentas, frameworks, plataformas e tecnologias de suporte | C2: 38 | D2: Frameworks e plataformas gerais | E2: 24 | F2: =E2/C2 -> 0.63157895 | G2: Percentual = Estudos_na_categoria / Total_RQ | H2: Sobreposta | I2: Predominante | J2: Categoria com maior incidência interna na RQ1; base para a principal tendência reportada. | K2: Percentuais calculados dentro da respectiva RQ; somas podem ultrapassar 100% por sobreposição.
A3: RQ1 | B3: Ferramentas, frameworks, plataformas e tecnologias de suporte | C3: 38 | D3: Plataformas especializadas por domínio | E3: 11 | F3: =E3/C3 -> 0.28947368 | G3: Percentual = Estudos_na_categoria / Total_RQ | H3: Sobreposta | I3: Recorrente | J3: Categoria recorrente na RQ1; indica dimensão relevante, mas secundária em relação à predominante. | K3: Percentuais calculados dentro da respectiva RQ; somas podem ultrapassar 100% por sobreposição.
A4: RQ1 | B4: Ferramentas, frameworks, plataformas e tecnologias de suporte | C4: 38 | D4: RAG, bases de conhecimento e memória | E4: 7 | F4: =E4/C4 -> 0.18421053 | G4: Percentual = Estudos_na_categoria / Total_RQ | H4: Sobreposta | I4: Menos recorrente / emergente | J4: Categoria menos recorrente/emergente na RQ1; indica dimensão ainda pouco consolidada ou especializada. | K4: Percentuais calculados dentro da respectiva RQ; somas podem ultrapassar 100% por sobreposição.
A5: RQ1 | B5: Ferramentas, frameworks, plataformas e tecnologias de suporte | C5: 38 | D5: Observabilidade, auditoria e governança | E5: 3 | F5: =E5/C5 -> 0.078947368 | G5: Percentual = Estudos_na_categoria / Total_RQ | H5: Sobreposta | I5: Menos recorrente / emergente | J5: Categoria menos recorrente/emergente na RQ1; indica dimensão ainda pouco consolidada ou especializada. | K5: Percentuais calculados dentro da respectiva RQ; somas podem ultrapassar 100% por sobreposição.
A6: RQ1 | B6: Ferramentas, frameworks, plataformas e tecnologias de suporte | C6: 38 | D6: Protocolos e interoperabilidade | E6: 2 | F6: =E6/C6 -> 0.052631579 | G6: Percentual = Estudos_na_categoria / Total_RQ | H6: Sobreposta | I6: Menos recorrente / emergente | J6: Categoria menos recorrente/emergente na RQ1; indica dimensão ainda pouco consolidada ou especializada. | K6: Percentuais calculados dentro da respectiva RQ; somas podem ultrapassar 100% por sobreposição.
A7: RQ2 | B7: Mecanismos de orquestração, comunicação, interoperabilidade, contexto e governança | C7: 75 | D7: Orquestração e coordenação de tarefas | E7: 61 | F7: =E7/C7 -> 0.81333333 | G7: Percentual = Estudos_na_categoria / Total_RQ | H7: Sobreposta | I7: Predominante | J7: Categoria com maior incidência interna na RQ2; base para a principal tendência reportada. | K7: Percentuais calculados dentro da respectiva RQ; somas podem ultrapassar 100% por sobreposição.
A8: RQ2 | B8: Mecanismos de orquestração, comunicação, interoperabilidade, contexto e governança | C8: 75 | D8: Comunicação e negociação entre agentes | E8: 12 | F8: =E8/C8 -> 0.16 | G8: Percentual = Estudos_na_categoria / Total_RQ | H8: Sobreposta | I8: Menos recorrente / emergente | J8: Categoria menos recorrente/emergente na RQ2; indica dimensão ainda pouco consolidada ou especializada. | K8: Percentuais calculados dentro da respectiva RQ; somas podem ultrapassar 100% por sobreposição.
A9: RQ2 | B9: Mecanismos de orquestração, comunicação, interoperabilidade, contexto e governança | C9: 75 | D9: Governança e humano-no-laço | E9: 7 | F9: =E9/C9 -> 0.093333333 | G9: Percentual = Estudos_na_categoria / Total_RQ | H9: Sobreposta | I9: Menos recorrente / emergente | J9: Categoria menos recorrente/emergente na RQ2; indica dimensão ainda pouco consolidada ou especializada. | K9: Percentuais calculados dentro da respectiva RQ; somas podem ultrapassar 100% por sobreposição.
A10: RQ2 | B10: Mecanismos de orquestração, comunicação, interoperabilidade, contexto e governança | C10: 75 | D10: Contexto, memória e conhecimento compartilhado | E10: 6 | F10: =E10/C10 -> 0.08 | G10: Percentual = Estudos_na_categoria / Total_RQ | H10: Sobreposta | I10: Menos recorrente / emergente | J10: Categoria menos recorrente/emergente na RQ2; indica dimensão ainda pouco consolidada ou especializada. | K10: Percentuais calculados dentro da respectiva RQ; somas podem ultrapassar 100% por sobreposição.
A11: RQ2 | B11: Mecanismos de orquestração, comunicação, interoperabilidade, contexto e governança | C11: 75 | D11: Interoperabilidade com ferramentas e serviços | E11: 5 | F11: =E11/C11 -> 0.066666667 | G11: Percentual = Estudos_na_categoria / Total_RQ | H11: Sobreposta | I11: Menos recorrente / emergente | J11: Categoria menos recorrente/emergente na RQ2; indica dimensão ainda pouco consolidada ou especializada. | K11: Percentuais calculados dentro da respectiva RQ; somas podem ultrapassar 100% por sobreposição.
A12: RQ3 | B12: Desafios, limitações, riscos e barreiras técnicas | C12: 21 | D12: Coordenação, alinhamento e decisão | E12: 15 | F12: =E12/C12 -> 0.71428571 | G12: Percentual = Estudos_na_categoria / Total_RQ | H12: Sobreposta | I12: Predominante | J12: Categoria com maior incidência interna na RQ3; base para a principal tendência reportada. | K12: Percentuais calculados dentro da respectiva RQ; somas podem ultrapassar 100% por sobreposição.
A13: RQ3 | B13: Desafios, limitações, riscos e barreiras técnicas | C13: 21 | D13: Comunicação, contexto e memória | E13: 4 | F13: =E13/C13 -> 0.19047619 | G13: Percentual = Estudos_na_categoria / Total_RQ | H13: Sobreposta | I13: Menos recorrente / emergente | J13: Categoria menos recorrente/emergente na RQ3; indica dimensão ainda pouco consolidada ou especializada. | K13: Percentuais calculados dentro da respectiva RQ; somas podem ultrapassar 100% por sobreposição.
... A32: RQ6 | B32: Lacunas de pesquisa e oportunidades futuras | C32: 14 | D32: Segurança, governança e auditabilidade | E32: 1 | F32: =E32/C32 -> 0.071428571 | G32: Percentual = Estudos_na_categoria / Total_RQ | H32: Sobreposta | I32: Menos recorrente / emergente | J32: Categoria menos recorrente/emergente na RQ6; indica dimensão ainda pouco consolidada ou especializada. | K32: Percentuais calculados dentro da respectiva RQ; somas podem ultrapassar 100% por sobreposição.
